Workbook

Sheet Dashboard
B2: SALES CASE STUDY — EXECUTIVE DASHBOARD
B3: Simulated daily trading data · single product · 30 Dec 2013 – 16 Nov 2016
B5: Total Sales | E5: Total Quantity Sold | H5: Overall Gross Profit % | K5: Avg Unit Price (weighted) | N5: Avg Daily GP %
B6: ='KPI Summary'!C8 -> 1.8690983e+08 | E6: ='KPI Summary'!C9 -> 1.9402611e+08 | H6: ='KPI Summary'!C11 -> -7116281.2 | K6: ='KPI Summary'!C14 -> 37.072852 | N6: ='KPI Summary'!C15 -> 35.400447
B43: Key Insights
B44: 1. Over the full 2013–2016 period the product is marginally loss-making overall (-3.8% gross profit), but the trend has turned: 2016 is the first year with a positive average gross profit margin (+2.6%), and 4 of the last 5 months in the dataset (Jul, Sep, Oct, Nov 2016) posted positive margins.
B46: 2. Demand for this product is highly price elastic. Across three tested promotional periods, PED ranged from -5.3 to -14.3 — a 10-15% price cut drove 50-170% more units sold per day.
B48: 3. That elasticity is a double-edged sword: every tested promo period had a negative gross profit % even though baseline (non-promo) margin was positive, meaning current promo discount depth is too aggressive relative to cost — volume gains do not offset the margin given away.
B50: 4. Weekends (especially Saturday) generate the highest average daily sales (~R279k) and volumes, but carry the thinnest margins of the week — weekend demand is more price-sensitive/promotion-driven.
B52: 5. Price and quantity are strongly negatively correlated (r ≈ -0.62) across the whole dataset, and price correlates positively with gross profit % (r ≈ +0.64) — confirming margin is protected at higher price points and volume is chased at lower ones.

Sheet Raw Data
A1: date | B1: sales | C1: cost_of_sales | D1: quantity_sold | E1: price_per_unit | F1: cost_per_unit | G1: gross_profit | H1: gross_profit_pct | I1: gross_profit_pct_per_unit | J1: year | K1: month | L1: week_of_year | M1: day_of_week | N1: is_weekend | O1: price_rolling_avg | P1: qty_rolling_avg | Q1: price_drop_pct | R1: qty_spike_pct | S1: promo_candidate
A2: 41638 | B2: 223937.97 | C2: 230079.62 | D2: 6827 | E2: 32.801812 | F2: 33.701424 | G2: -6141.6531 | H2: -0.027425689 | I2: -0.027425689 | J2: 2013 | K2: 12 | L2: 1 | M2: Monday | N2: =FALSE() -> FALSE | S2: =FALSE() -> FALSE
A3: 41639 | B3: 300345.48 | C3: 306986.12 | D3: 9268 | E3: 32.40672 | F3: 33.123233 | G3: -6640.6359 | H3: -0.022109991 | I3: -0.022109991 | J3: 2013 | K3: 12 | L3: 1 | M3: Tuesday | N3: =FALSE() -> FALSE | O3: 32.801812 | P3: 6827 | Q3: -0.012044799 | R3: 0.3575509 | S3: =FALSE() -> FALSE
A4: 41640 | B4: 86782.468 | C4: 87986.318 | D4: 2678 | E4: 32.405701 | F4: 32.855235 | G4: -1203.8505 | H4: -0.013872047 | I4: -0.013872047 | J4: 2014 | K4: 1 | L4: 1 | M4: Wednesday | N4: =FALSE() -> FALSE | O4: 32.604266 | P4: 8047.5 | Q4: -0.0060901488 | R4: -0.66722585 | S4: =FALSE() -> FALSE
A5: 41641 | B5: 200173.12 | C5: 202881.18 | D5: 6175 | E5: 32.416699 | F5: 32.855251 | G5: -2708.061 | H5: -0.013528595 | I5: -0.013528595 | J5: 2014 | K5: 1 | L5: 1 | M5: Thursday | N5: =FALSE() -> FALSE | O5: 32.538078 | P5: 6257.6667 | Q5: -0.0037303572 | R5: -0.013210462 | S5: =FALSE() -> FALSE
A6: 41642 | B6: 326906.07 | C6: 333806.29 | D6: 10084 | E6: 32.418294 | F6: 33.102568 | G6: -6900.2177 | H6: -0.021107646 | I6: -0.021107646 | J6: 2014 | K6: 1 | L6: 1 | M6: Friday | N6: =FALSE() -> FALSE | O6: 32.507733 | P6: 6237 | Q6: -0.0027513241 | R6: 0.61680295 | S6: =FALSE() -> FALSE
A7: 41643 | B7: 307043.94 | C7: 313652.35 | D7: 9470 | E7: 32.422802 | F7: 33.120628 | G7: -6608.4129 | H7: -0.021522695 | I7: -0.021522695 | J7: 2014 | K7: 1 | L7: 1 | M7: Saturday | N7: =TRUE() -> TRUE | O7: 32.489845 | P7: 7006.4 | Q7: -0.0020635108 | R7: 0.35162137 | S7: =FALSE() -> FALSE
A8: 41644 | B8: 179188.88 | C8: 183083.28 | D8: 5524 | E8: 32.438248 | F8: 33.143245 | G8: -3894.4005 | H8: -0.021733494 | I8: -0.021733494 | J8: 2014 | K8: 1 | L8: 1 | M8: Sunday | N8: =TRUE() -> TRUE | O8: 32.478671 | P8: 7417 | Q8: -0.0012445977 | R8: -0.25522448 | S8: =FALSE() -> FALSE
A9: 41645 | B9: 306351.95 | C9: 313446.07 | D9: 9448 | E9: 32.425058 | F9: 33.175917 | G9: -7094.1173 | H9: -0.023156756 | I9: -0.023156756 | J9: 2014 | K9: 1 | L9: 2 | M9: Monday | N9: =FALSE() -> FALSE | O9: 32.472897 | P9: 7146.5714 | Q9: -0.0014731774 | R9: 0.32203254 | S9: =FALSE() -> FALSE
A10: 41646 | B10: 224020.41 | C10: 229533.97 | D10: 6911 | E10: 32.41505 | F10: 33.212845 | G10: -5513.5638 | H10: -0.024611881 | I10: -0.024611881 | J10: 2014 | K10: 1 | L10: 2 | M10: Tuesday | N10: =FALSE() -> FALSE | O10: 32.466917 | P10: 7434.25 | Q10: -0.0015975319 | R10: -0.070383697 | S10: =FALSE() -> FALSE
A11: 41647 | B11: 101836.4 | C11: 99381.968 | D11: 2990 | E11: 34.058997 | F11: 33.238116 | G11: 2454.4347 | H11: 0.024101742 | I11: 0.024101742 | J11: 2014 | K11: 1 | L11: 2 | M11: Wednesday | N11: =FALSE() -> FALSE | O11: 32.461154 | P11: 7376.1111 | Q11: 0.049223252 | R11: -0.59463734 | S11: =FALSE() -> FALSE
A12: 41648 | B12: 107804.3 | C12: 104816.46 | D12: 3159 | E12: 34.126086 | F12: 33.180265 | G12: 2987.8464 | H12: 0.027715465 | I12: 0.027715465 | J12: 2014 | K12: 1 | L12: 2 | M12: Thursday | N12: =FALSE() -> FALSE | O12: 32.620938 | P12: 6937.5 | Q12: 0.046140536 | R12: -0.54464865 | S12: =FALSE() -> FALSE
A13: 41649 | B13: 144829.96 | C13: 141334 | D13: 4246 | E13: 34.10974 | F13: 33.286386 | G13: 3495.9604 | H13: 0.024138379 | I13: 0.024138379 | J13: 2014 | K13: 1 | L13: 2 | M13: Friday | N13: =FALSE() -> FALSE | O13: 32.75777 | P13: 6594 | Q13: 0.041271746 | R13: -0.35608129 | S13: =FALSE() -> FALSE
A14: 41650 | B14: 146571.48 | C14: 143179.67 | D14: 4297 | E14: 34.110189 | F14: 33.320845 | G14: 3391.8124 | H14: 0.023141012 | I14: 0.023141012 | J14: 2014 | K14: 1 | L14: 2 | M14: Saturday | N14: =TRUE() -> TRUE | O14: 32.870434 | P14: 6398.3333 | Q14: 0.037716419 | R14: -0.32841886 | S14: =FALSE() -> FALSE
A15: 41651 | B15: 95422.373 | C15: 93126.147 | D15: 2796 | E15: 34.128173 | F15: 33.30692 | G15: 2296.2257 | H15: 0.024063809 | I15: 0.024063809 | J15: 2014 | K15: 1 | L15: 2 | M15: Sunday | N15: =TRUE() -> TRUE | O15: 32.9658 | P15: 6236.6923 | Q15: 0.035259987 | R15: -0.55168543 | S15: =FALSE() -> FALSE
A16: 41652 | B16: 114883.17 | C16: 112186.31 | D16: 3369 | E16: 34.100081 | F16: 33.299587 | G16: 2696.8651 | H16: 0.023474849 | I16: 0.023474849 | J16: 2014 | K16: 1 | L16: 3 | M16: Monday | N16: =FALSE() -> FALSE | O16: 33.048826 | P16: 5990.9286 | Q16: 0.031809142 | R16: -0.43764978 | S16: =FALSE() -> FALSE
A17: 41653 | B17: 80090.8 | C17: 78096.76 | D17: 2348 | E17: 34.110221 | F17: 33.260971 | G17: 1994.0399 | H17: 0.02489724 | I17: 0.02489724 | J17: 2014 | K17: 1 | L17: 3 | M17: Tuesday | N17: =FALSE() -> FALSE | O17: 33.14156 | P17: 5743.9286 | Q17: 0.029227999 | R17: -0.59122054 | S17: =FALSE() -> FALSE
A18: 41654 | B18: 98945.371 | C18: 97159.003 | D18: 2903 | E18: 34.083834 | F18: 33.468482 | G18: 1786.3686 | H18: 0.018054089 | I18: 0.018054089 | J18: 2014 | K18: 1 | L18: 3 | M18: Wednesday | N18: =FALSE() -> FALSE | O18: 33.263239 | P18: 5249.6429 | Q18: 0.024669747 | R18: -0.44701 | S18: =FALSE() -> FALSE
A19: 41655 | B19: 84904.902 | C19: 83350.433 | D19: 2491 | E19: 34.084665 | F19: 33.460632 | G19: 1554.4686 | H19: 0.018308349 | I19: 0.018308349 | J19: 2014 | K19: 1 | L19: 3 | M19: Thursday | N19: =FALSE() -> FALSE | O19: 33.383105 | P19: 5265.7143 | Q19: 0.021015425 | R19: -0.52693977 | S19: =FALSE() -> FALSE
A20: 41656 | B20: 135460.62 | C20: 132703.34 | D20: 3968 | E20: 34.138261 | F20: 33.443381 | G20: 2757.2843 | H20: 0.020354877 | I20: 0.020354877 | J20: 2014 | K20: 1 | L20: 3 | M20: Friday | N20: =FALSE() -> FALSE | O20: 33.502246 | P20: 5002.5714 | Q20: 0.018984257 | R20: -0.20680793 | S20: =FALSE() -> FALSE
A21: 41657 | B21: 149925.75 | C21: 146928.41 | D21: 4393 | E21: 34.128329 | F21: 33.44603 | G21: 2997.3379 | H21: 0.019992149 | I21: 0.019992149 | J21: 2014 | K21: 1 | L21: 3 | M21: Saturday | N21: =TRUE() -> TRUE | O21: 33.625101 | P21: 4565.7143 | Q21: 0.014965859 | R21: -0.037828536 | S21: =FALSE() -> FALSE
A22: 41658 | B22: 74297.307 | C22: 72782.284 | D22: 2176 | E22: 34.143983 | F22: 33.447741 | G22: 1515.0229 | H22: 0.020391356 | I22: 0.020391356 | J22: 2014 | K22: 1 | L22: 3 | M22: Sunday | N22: =TRUE() -> TRUE | O22: 33.746924 | P22: 4203.0714 | Q22: 0.011765787 | R22: -0.48228336 | S22: =FALSE() -> FALSE
A23: 41659 | B23: 83356.425 | C23: 81789.136 | D23: 2443 | E23: 34.120518 | F23: 33.478975 | G23: 1567.2884 | H23: 0.018802251 | I23: 0.018802251 | J23: 2014 | K23: 1 | L23: 4 | M23: Monday | N23: =FALSE() -> FALSE | O23: 33.868762 | P23: 3963.9286 | Q23: 0.0074332653 | R23: -0.38369222 | S23: =FALSE() -> FALSE
A24: 41660 | B24: 89922.014 | C24: 88388.916 | D24: 2638 | E24: 34.087193 | F24: 33.506033 | G24: 1533.0982 | H24: 0.017049198 | I24: 0.017049198 | J24: 2014 | K24: 1 | L24: 4 | M24: Tuesday | N24: =FALSE() -> FALSE | O24: 33.989866 | P24: 3463.5714 | Q24: 0.0028633919 | R24: -0.23835842 | S24: =FALSE() -> FALSE
A25: 41661 | B25: 57806.303 | C25: 57157.283 | D25: 1704 | E25: 33.923887 | F25: 33.543006 | G25: 649.02024 | H25: 0.0112275 | I25: 0.0112275 | J25: 2014 | K25: 1 | L25: 4 | M25: Wednesday | N25: =FALSE() -> FALSE | O25: 34.109305 | P25: 3158.3571 | Q25: -0.0054360102 | R25: -0.460479 | S25: =FALSE() -> FALSE
A26: 41662 | B26: 63977.75 | C26: 62863.987 | D26: 1872 | E26: 34.176149 | F26: 33.58119 | G26: 1113.7631 | H26: 0.017408601 | I26: 0.017408601 | J26: 2014 | K26: 1 | L26: 4 | M26: Thursday | N26: =FALSE() -> FALSE | O26: 34.099654 | P26: 3066.5 | Q26: 0.002243258 | R26: -0.38953204 | S26: =FALSE() -> FALSE
A27: 41663 | B27: 116958.8 | C27: 114823.8 | D27: 3423 | E27: 34.168507 | F27: 33.544784 | G27: 2135.0046 | H27: 0.018254331 | I27: 0.018254331 | J27: 2014 | K27: 1 | L27: 4 | M27: Friday | N27: =FALSE() -> FALSE | O27: 34.10323 | P27: 2974.5714 | Q27: 0.001914095 | R27: 0.15075401 | S27: =FALSE() -> FALSE
A28: 41664 | B28: 155272.82 | C28: 152636.28 | D28: 4544 | E28: 34.170956 | F28: 33.59073 | G28: 2636.5482 | H28: 0.016980101 | I28: 0.016980101 | J28: 2014 | K28: 1 | L28: 4 | M28: Saturday | N28: =TRUE() -> TRUE | O28: 34.107428 | P28: 2915.7857 | Q28: 0.0018625923 | R28: 0.55841356 | S28: =FALSE() -> FALSE
A29: 41665 | B29: 82885.216 | C29: 81583.167 | D29: 2426 | E29: 34.165382 | F29: 33.628676 | G29: 1302.049 | H29: 0.015709062 | I29: 0.015709062 | J29: 2014 | K29: 1 | L29: 4 | M29: Sunday | N29: =TRUE() -> TRUE | O29: 34.111768 | P29: 2933.4286 | Q29: 0.0015716929 | R29: -0.1729814 | S29: =FALSE() -> FALSE
A30: 41666 | B30: 72353.426 | C30: 71377.156 | D30: 2117 | E30: 34.177339 | F30: 33.716182 | G30: 976.26943 | H30: 0.013493064 | I30: 0.013493064 | J30: 2014 | K30: 1 | L30: 5 | M30: Monday | N30: =FALSE() -> FALSE | O30: 34.114426 | P30: 2907 | Q30: 0.0018441601 | R30: -0.27175783 | S30: =FALSE() -> FALSE
A31: 41667 | B31: 50415.904 | C31: 49769.098 | D31: 1476 | E31: 34.157116 | F31: 33.718901 | G31: 646.80552 | H31: 0.012829395 | I31: 0.012829395 | J31: 2014 | K31: 1 | L31: 5 | M31: Tuesday | N31: =FALSE() -> FALSE | O31: 34.119945 | P31: 2817.5714 | Q31: 0.0010894455 | R31: -0.4761446 | S31: =FALSE() -> FALSE
A32: 41668 | B32: 67458.302 | C32: 66529.442 | D32: 1974 | E32: 34.173405 | F32: 33.702858 | G32: 928.85989 | H32: 0.013769393 | I32: 0.013769393 | J32: 2014 | K32: 1 | L32: 5 | M32: Wednesday | N32: =FALSE() -> FALSE | O32: 34.123294 | P32: 2755.2857 | Q32: 0.0014685285 | R32: -0.28355887 | S32: =FALSE() -> FALSE
A33: 41669 | B33: 64640.369 | C33: 63757.84 | D33: 1892 | E33: 34.1651 | F33: 33.698647 | G33: 882.52944 | H33: 0.013652915 | I33: 0.013652915 | J33: 2014 | K33: 1 | L33: 5 | M33: Thursday | N33: =FALSE() -> FALSE | O33: 34.129692 | P33: 2688.9286 | Q33: 0.0010374532 | R33: -0.29637402 | S33: =FALSE() -> FALSE
A34: 41670 | B34: 137693.87 | C34: 135609.51 | D34: 4030 | E34: 34.167214 | F34: 33.650002 | G34: 2084.3659 | H34: 0.015137681 | I34: 0.015137681 | J34: 2014 | K34: 1 | L34: 5 | M34: Friday | N34: =FALSE() -> FALSE | O34: 34.135437 | P34: 2646.1429 | Q34: 0.00093090471 | R34: 0.52297144 | S34: =FALSE() -> FALSE
A35: 41671 | B35: 181209.13 | C35: 178435.72 | D35: 5304 | E35: 34.164617 | F35: 33.641726 | G35: 2773.4131 | H35: 0.015305041 | I35: 0.015305041 | J35: 2014 | K35: 2 | L35: 5 | M35: Saturday | N35: =TRUE() -> TRUE | O35: 34.137506 | P35: 2650.5714 | Q35: 0.00079418414 | R35: 1.0010779 | S35: =FALSE() -> FALSE
A36: 41672 | B36: 113433.58 | C36: 111466.52 | D36: 3320 | E36: 34.166741 | F36: 33.574252 | G36: 1967.0642 | H36: 0.01734111 | I36: 0.01734111 | J36: 2014 | K36: 2 | L36: 5 | M36: Sunday | N36: =TRUE() -> TRUE | O36: 34.140098 | P36: 2715.6429 | Q36: 0.00078042449 | R36: 0.22254662 | S36: =FALSE() -> FALSE
A37: 41673 | B37: 143192.53 | C37: 140505.63 | D37: 4191 | E37: 34.166675 | F37: 33.525563 | G37: 2686.8986 | H37: 0.018764237 | I37: 0.018764237 | J37: 2014 | K37: 2 | L37: 6 | M37: Monday | N37: =FALSE() -> FALSE | O37: 34.141723 | P37: 2797.3571 | Q37: 0.00073082221 | R37: 0.49819983 | S37: =FALSE() -> FALSE
A38: 41674 | B38: 130126.65 | C38: 128496.29 | D38: 3809 | E38: 34.162943 | F38: 33.734914 | G38: 1630.3622 | H38: 0.012529041 | I38: 0.012529041 | J38: 2014 | K38: 2 | L38: 6 | M38: Tuesday | N38: =FALSE() -> FALSE | O38: 34.14502 | P38: 2922.2143 | Q38: 0.00052490749 | R38: 0.30346362 | S38: =FALSE() -> FALSE
A39: 41675 | B39: 187155.87 | C39: 195078.6 | D39: 5764 | E39: 32.46979 | F39: 33.84431 | G39: -7922.7348 | H39: -0.042332281 | I39: -0.042332281 | J39: 2014 | K39: 2 | L39: 6 | M39: Wednesday | N39: =FALSE() -> FALSE | O39: 34.150431 | P39: 3005.8571 | Q39: -0.049212877 | R39: 0.91758947 | S39: =FALSE() -> FALSE
A40: 41676 | B40: 102314.71 | C40: 101977.99 | D40: 3028 | E40: 33.789534 | F40: 33.678332 | G40: 336.71964 | H40: 0.0032910189 | I40: 0.0032910189 | J40: 2014 | K40: 2 | L40: 6 | M40: Thursday | N40: =FALSE() -> FALSE | O40: 34.046567 | P40: 3295.8571 | Q40: -0.0075494394 | R40: -0.08127086 | S40: =FALSE() -> FALSE
A41: 41677 | B41: 301553.84 | C41: 313529.19 | D41: 9284 | E41: 32.481026 | F41: 33.770916 | G41: -11975.345 | H41: -0.039712129 | I41: -0.039712129 | J41: 2014 | K41: 2 | L41: 6 | M41: Friday | N41: =FALSE() -> FALSE | O41: 34.018951 | P41: 3378.4286 | Q41: -0.04520791 | R41: 1.7480232 | S41: =FALSE() -> FALSE
A42: 41678 | B42: 316073.18 | C42: 329754.78 | D42: 9737 | E42: 32.461043 | F42: 33.866158 | G42: -13681.602 | H42: -0.043286185 | I42: -0.043286185 | J42: 2014 | K42: 2 | L42: 6 | M42: Saturday | N42: =TRUE() -> TRUE | O42: 33.898417 | P42: 3797.0714 | Q42: -0.042402387 | R42: 1.5643447 | S42: =FALSE() -> FALSE
A43: 41679 | B43: 135178.04 | C43: 141530.71 | D43: 4163 | E43: 32.471305 | F43: 33.997288 | G43: -6352.6661 | H43: -0.046994808 | I43: -0.046994808 | J43: 2014 | K43: 2 | L43: 6 | M43: Sunday | N43: =TRUE() -> TRUE | O43: 33.77628 | P43: 4168 | Q43: -0.038635853 | R43: -0.0011996161 | S43: =FALSE() -> FALSE
A44: 41680 | B44: 147727.52 | C44: 154828.68 | D44: 4552 | E44: 32.453321 | F44: 34.013331 | G44: -7101.1684 | H44: -0.048069368 | I44: -0.048069368 | J44: 2014 | K44: 2 | L44: 7 | M44: Monday | N44: =FALSE() -> FALSE | O44: 33.655275 | P44: 4292.0714 | Q44: -0.035713691 | R44: 0.060560169 | S44: =FALSE() -> FALSE
A45: 41681 | B45: 135498.75 | C45: 139824.16 | D45: 4172 | E45: 32.478127 | F45: 33.5149 | G45: -4325.4152 | H45: -0.031922179 | I45: -0.031922179 | J45: 2014 | K45: 2 | L45: 7 | M45: Tuesday | N45: =FALSE() -> FALSE | O45: 33.532131 | P45: 4466 | Q45: -0.031432646 | R45: -0.065830721 | S45: =FALSE() -> FALSE
A46: 41682 | B46: 163432.85 | C46: 166893.37 | D46: 5037 | E46: 32.446465 | F46: 33.133486 | G46: -3460.5237 | H46: -0.021173979 | I46: -0.021173979 | J46: 2014 | K46: 2 | L46: 7 | M46: Wednesday | N46: =FALSE() -> FALSE | O46: 33.412203 | P46: 4658.5714 | Q46: -0.028903744 | R46: 0.081232751 | S46: =FALSE() -> FALSE
A47: 41683 | B47: 138291.63 | C47: 141027.43 | D47: 4259 | E47: 32.470447 | F47: 33.112805 | G47: -2735.8011 | H47: -0.019782839 | I47: -0.019782839 | J47: 2014 | K47: 2 | L47: 7 | M47: Thursday | N47: =FALSE() -> FALSE | O47: 33.28885 | P47: 4877.3571 | Q47: -0.024584904 | R47: -0.12678119 | S47: =FALSE() -> FALSE
A48: 41684 | B48: 336901.37 | C48: 343519.88 | D48: 10381 | E48: 32.453653 | F48: 33.091212 | G48: -6618.5038 | H48: -0.019645227 | I48: -0.019645227 | J48: 2014 | K48: 2 | L48: 7 | M48: Friday | N48: =FALSE() -> FALSE | O48: 33.167803 | P48: 5046.4286 | Q48: -0.021531436 | R48: 1.0570984 | S48: =FALSE() -> FALSE
A49: 41685 | B49: 367729.27 | C49: 373973.59 | D49: 11332 | E49: 32.450518 | F49: 33.001553 | G49: -6244.3251 | H49: -0.016980767 | I49: -0.016980767 | J49: 2014 | K49: 2 | L49: 7 | M49: Saturday | N49: =TRUE() -> TRUE | O49: 33.045406 | P49: 5500.0714 | Q49: -0.01800215 | R49: 1.0603369 | S49: =FALSE() -> FALSE
A50: 41686 | B50: 133913.84 | C50: 136797.08 | D50: 4127 | E50: 32.448229 | F50: 33.146857 | G50: -2883.236 | H50: -0.02153053 | I50: -0.02153053 | J50: 2014 | K50: 2 | L50: 7 | M50: Sunday | N50: =TRUE() -> TRUE | O50: 32.922971 | P50: 5930.6429 | Q50: -0.014419764 | R50: -0.30412266 | S50: =FALSE() -> FALSE
A51: 41687 | B51: 150800.35 | C51: 152887.11 | D51: 4649 | E51: 32.437158 | F51: 32.88602 | G51: -2086.7594 | H51: -0.013837895 | I51: -0.013837895 | J51: 2014 | K51: 2 | L51: 8 | M51: Monday | N51: =FALSE() -> FALSE | O51: 32.80022 | P51: 5988.2857 | Q51: -0.011068883 | R51: -0.22365094 | S51: =FALSE() -> FALSE
A52: 41688 | B52: 55591.93 | C52: 53463.244 | D52: 1627 | E52: 34.168365 | F52: 32.860015 | G52: 2128.6861 | H52: 0.038291279 | I52: 0.038291279 | J52: 2014 | K52: 2 | L52: 8 | M52: Tuesday | N52: =FALSE() -> FALSE | O52: 32.676683 | P52: 6021 | Q52: 0.045649754 | R52: -0.72977911 | S52: =FALSE() -> FALSE
A53: 41689 | B53: 106427.19 | C53: 107736.44 | D53: 3281 | E53: 32.437425 | F53: 32.836466 | G53: -1309.2522 | H53: -0.012301858 | I53: -0.012301858 | J53: 2014 | K53: 2 | L53: 8 | M53: Wednesday | N53: =FALSE() -> FALSE | O53: 32.67707 | P53: 5865.1429 | Q53: -0.0073337342 | R53: -0.44059334 | S53: =FALSE() -> FALSE
A54: 41690 | B54: 78940.554 | C54: 75934.395 | D54: 2310 | E54: 34.1734 | F54: 32.872032 | G54: 3006.1596 | H54: 0.038081308 | I54: 0.038081308 | J54: 2014 | K54: 2 | L54: 8 | M54: Thursday | N54: =FALSE() -> FALSE | O54: 32.674758 | P54: 5687.7857 | Q54: 0.045865431 | R54: -0.59386656 | S54: =FALSE() -> FALSE
A55: 41691 | B55: 317916.32 | C55: 322089.79 | D55: 9802 | E55: 32.433821 | F55: 32.859599 | G55: -4173.4711 | H55: -0.013127577 | I55: -0.013127577 | J55: 2014 | K55: 2 | L55: 8 | M55: Friday | N55: =FALSE() -> FALSE | O55: 32.702177 | P55: 5636.5 | Q55: -0.0082060546 | R55: 0.73902244 | S55: =FALSE() -> FALSE
A56: 41692 | B56: 309217.88 | C56: 320116.92 | D56: 9772 | E56: 31.643254 | F56: 32.758588 | G56: -10899.049 | H56: -0.03524715 | I56: -0.03524715 | J56: 2014 | K56: 2 | L56: 8 | M56: Saturday | N56: =TRUE() -> TRUE | O56: 32.698806 | P56: 5673.5 | Q56: -0.032281052 | R56: 0.72239358 | S56: =FALSE() -> FALSE
A57: 41693 | B57: 138491.55 | C57: 140752.6 | D57: 4270 | E57: 32.433618 | F57: 32.963139 | G57: -2261.0516 | H57: -0.016326279 | I57: -0.016326279 | J57: 2014 | K57: 2 | L57: 8 | M57: Sunday | N57: =TRUE() -> TRUE | O57: 32.640392 | P57: 5676 | Q57: -0.0063349051 | R57: -0.24770965 | S57: =FALSE() -> FALSE
A58: 41694 | B58: 133146.22 | C58: 134505.4 | D58: 4106 | E58: 32.427234 | F58: 32.758257 | G58: -1359.182 | H58: -0.010208191 | I58: -0.010208191 | J58: 2014 | K58: 2 | L58: 9 | M58: Monday | N58: =FALSE() -> FALSE | O58: 32.6377 | P58: 5683.6429 | Q58: -0.0064485634 | R58: -0.277576 | S58: =FALSE() -> FALSE
A59: 41695 | B59: 224994.66 | C59: 227546.45 | D59: 6937 | E59: 32.434 | F59: 32.801852 | G59: -2551.7904 | H59: -0.01134156 | I59: -0.01134156 | J59: 2014 | K59: 2 | L59: 9 | M59: Tuesday | N59: =FALSE() -> FALSE | O59: 32.635837 | P59: 5651.7857 | Q59: -0.0061845218 | R59: 0.22739968 | S59: =FALSE() -> FALSE
A60: 41696 | B60: 225051.59 | C60: 228214.14 | D60: 6934 | E60: 32.456243 | F60: 32.912337 | G60: -3162.5507 | H60: -0.014052558 | I60: -0.014052558 | J60: 2014 | K60: 2 | L60: 9 | M60: Wednesday | N60: =FALSE() -> FALSE | O60: 32.632685 | P60: 5849.2857 | Q60: -0.0054068938 | R60: 0.18544389 | S60: =FALSE() -> FALSE
A61: 41697 | B61: 344299.68 | C61: 365935.65 | D61: 11082 | E61: 31.068371 | F61: 33.020723 | G61: -21635.971 | H61: -0.062840518 | I61: -0.062840518 | J61: 2014 | K61: 2 | L61: 9 | M61: Thursday | N61: =FALSE() -> FALSE | O61: 32.633383 | P61: 5984.7857 | Q61: -0.047957415 | R61: 0.85169537 | S61: =FALSE() -> FALSE
A62: 41698 | B62: 661876.5 | C62: 686656.79 | D62: 20805 | E62: 31.813338 | F62: 33.004412 | G62: -24780.291 | H62: -0.037439448 | I62: -0.037439448 | J62: 2014 | K62: 2 | L62: 9 | M62: Friday | N62: =FALSE() -> FALSE | O62: 32.533235 | P62: 6472.1429 | Q62: -0.022128043 | R62: 2.2145459 | S62: =FALSE() -> FALSE
A63: 41699 | B63: 846678.39 | C63: 872081.59 | D63: 26410 | E63: 32.059008 | F63: 33.020885 | G63: -25403.197 | H63: -0.03000336 | I63: -0.03000336 | J63: 2014 | K63: 3 | L63: 9 | M63: Saturday | N63: =TRUE() -> TRUE | O63: 32.487498 | P63: 7216.7143 | Q63: -0.013189402 | R63: 2.6595601 | S63: =FALSE() -> FALSE
A64: 41700 | B64: 478902.3 | C64: 495554.45 | D64: 15004 | E64: 31.918309 | F64: 33.028156 | G64: -16652.145 | H64: -0.034771487 | I64: -0.034771487 | J64: 2014 | K64: 3 | L64: 9 | M64: Sunday | N64: =TRUE() -> TRUE | O64: 32.459533 | P64: 8293.7143 | Q64: -0.016673819 | R64: 0.80908089 | S64: =FALSE() -> FALSE
A65: 41701 | B65: 538827.2 | C65: 557567.14 | D65: 16884 | E65: 31.91348 | F65: 33.023403 | G65: -18739.935 | H65: -0.034779118 | I65: -0.034779118 | J65: 2014 | K65: 3 | L65: 10 | M65: Monday | N65: =FALSE() -> FALSE | O65: 32.421682 | P65: 9070.6429 | Q65: -0.015674738 | R65: 0.86138957 | S65: =FALSE() -> FALSE
A66: 41702 | B66: 310346.12 | C66: 323325.03 | D66: 9789 | E66: 31.703557 | F66: 33.029424 | G66: -12978.909 | H66: -0.041820754 | I66: -0.041820754 | J66: 2014 | K66: 3 | L66: 10 | M66: Tuesday | N66: =FALSE() -> FALSE | O66: 32.384276 | P66: 9944.5714 | Q66: -0.021020046 | R66: -0.015643855 | S66: =FALSE() -> FALSE
A67: 41703 | B67: 256390.52 | C67: 267308.51 | D67: 8079 | E67: 31.735428 | F67: 33.086831 | G67: -10917.985 | H67: -0.042583418 | I67: -0.042583418 | J67: 2014 | K67: 3 | L67: 10 | M67: Wednesday | N67: =FALSE() -> FALSE | O67: 32.208218 | P67: 10527.571 | Q67: -0.014679189 | R67: -0.23258654 | S67: =FALSE() -> FALSE
A68: 41704 | B68: 167803.66 | C68: 168135.69 | D68: 5072 | E68: 33.084318 | F68: 33.149781 | G68: -332.03023 | H68: -0.0019786829 | I68: -0.0019786829 | J68: 2014 | K68: 3 | L68: 10 | M68: Thursday | N68: =FALSE() -> FALSE | O68: 32.158076 | P68: 10870.286 | Q68: 0.02880278 | R68: -0.53340693 | S68: =FALSE() -> FALSE
A69: 41705 | B69: 465318.02 | C69: 483774.6 | D69: 14551 | E69: 31.978422 | F69: 33.246828 | G69: -18456.575 | H69: -0.039664432 | I69: -0.039664432 | J69: 2014 | K69: 3 | L69: 10 | M69: Friday | N69: =FALSE() -> FALSE | O69: 32.080284 | P69: 11067.571 | Q69: -0.0031752206 | R69: 0.31474191 | S69: =FALSE() -> FALSE
A70: 41706 | B70: 520146.75 | C70: 541498.96 | D70: 16262 | E70: 31.985411 | F70: 33.298423 | G70: -21352.209 | H70: -0.041050355 | I70: -0.041050355 | J70: 2014 | K70: 3 | L70: 10 | M70: Saturday | N70: =TRUE() -> TRUE | O70: 32.047756 | P70: 11406.786 | Q70: -0.0019453755 | R70: 0.42564263 | S70: =FALSE() -> FALSE
A71: 41707 | B71: 224699.25 | C71: 233589.98 | D71: 7014 | E71: 32.035822 | F71: 33.303391 | G71: -8890.7301 | H71: -0.039567244 | I71: -0.039567244 | J71: 2014 | K71: 3 | L71: 10 | M71: Sunday | N71: =TRUE() -> TRUE | O71: 32.072195 | P71: 11870.357 | Q71: -0.0011341237 | R71: -0.40911635 | S71: =FALSE() -> FALSE
A72: 41708 | B72: 286230.68 | C72: 297642.89 | D72: 8932 | E72: 32.045531 | F72: 33.323208 | G72: -11412.213 | H72: -0.039870683 | I72: -0.039870683 | J72: 2014 | K72: 3 | L72: 11 | M72: Monday | N72: =FALSE() -> FALSE | O72: 32.043781 | P72: 12066.357 | Q72: 5.4586045e-05 | R72: -0.25976002 | S72: =FALSE() -> FALSE
A73: 41709 | B73: 187143.02 | C73: 191499.04 | D73: 5737 | E73: 32.620362 | F73: 33.379648 | G73: -4356.0248 | H73: -0.023276448 | I73: -0.023276448 | J73: 2014 | K73: 3 | L73: 11 | M73: Tuesday | N73: =FALSE() -> FALSE | O73: 32.016517 | P73: 12411.071 | Q73: 0.018860432 | R73: -0.53775143 | S73: =FALSE() -> FALSE
A74: 41710 | B74: 191700.39 | C74: 197153.42 | D74: 5903 | E74: 32.475079 | F74: 33.398852 | G74: -5453.0349 | H74: -0.028445612 | I74: -0.028445612 | J74: 2014 | K74: 3 | L74: 11 | M74: Wednesday | N74: =FALSE() -> FALSE | O74: 32.029828 | P74: 12325.357 | Q74: 0.013901109 | R74: -0.52106864 | S74: =FALSE() -> FALSE
A75: 41711 | B75: 164663.97 | C75: 168975.17 | D75: 5056 | E75: 32.568032 | F75: 33.420723 | G75: -4311.2064 | H75: -0.026181845 | I75: -0.026181845 | J75: 2014 | K75: 3 | L75: 11 | M75: Thursday | N75: =FALSE() -> FALSE | O75: 32.031174 | P75: 12251.714 | Q75: 0.016760475 | R75: -0.58732306 | S75: =FALSE() -> FALSE
A76: 41712 | B76: 395941.35 | C76: 406765.91 | D76: 12167 | E76: 32.542233 | F76: 33.431899 | G76: -10824.569 | H76: -0.027338819 | I76: -0.027338819 | J76: 2014 | K76: 3 | L76: 11 | M76: Friday | N76: =FALSE() -> FALSE | O76: 32.138293 | P76: 11821.286 | Q76: 0.012568813 | R76: 0.029245066 | S76: =FALSE() -> FALSE
A77: 41713 | B77: 518183.21 | C77: 534383.14 | D77: 15971 | E77: 32.445258 | F77: 33.459592 | G77: -16199.933 | H77: -0.031262944 | I77: -0.031262944 | J77: 2014 | K77: 3 | L77: 11 | M77: Saturday | N77: =TRUE() -> TRUE | O77: 32.190356 | P77: 11204.286 | Q77: 0.00791856 | R77: 0.4254367 | S77: =FALSE() -> FALSE
A78: 41714 | B78: 226617.95 | C78: 233191.1 | D78: 6968 | E78: 32.522669 | F78: 33.466002 | G78: -6573.1496 | H78: -0.029005423 | I78: -0.029005423 | J78: 2014 | K78: 3 | L78: 11 | M78: Sunday | N78: =TRUE() -> TRUE | O78: 32.217946 | P78: 10458.643 | Q78: 0.0094581732 | R78: -0.33375677 | S78: =FALSE() -> FALSE
A79: 41715 | B79: 243707.87 | C79: 250794.22 | D79: 7494 | E79: 32.520399 | F79: 33.466002 | G79: -7086.3493 | H79: -0.029077228 | I79: -0.029077228 | J79: 2014 | K79: 3 | L79: 12 | M79: Monday | N79: =FALSE() -> FALSE | O79: 32.261114 | P79: 9884.6429 | Q79: 0.0080370744 | R79: -0.24185425 | S79: =FALSE() -> FALSE
A80: 41716 | B80: 94849.744 | C80: 90571.589 | D80: 2707 | E80: 35.038694 | F80: 33.458289 | G80: 4278.1549 | H80: 0.045104549 | I80: 0.045104549 | J80: 2014 | K80: 3 | L80: 12 | M80: Tuesday | N80: =FALSE() -> FALSE | O80: 32.304466 | P80: 9213.9286 | Q80: 0.084639322 | R80: -0.70620567 | S80: =FALSE() -> FALSE
A81: 41717 | B81: 92386.783 | C81: 88255.841 | D81: 2637 | E81: 35.034806 | F81: 33.468275 | G81: 4130.9421 | H81: 0.044713561 | I81: 0.044713561 | J81: 2014 | K81: 3 | L81: 12 | M81: Wednesday | N81: =FALSE() -> FALSE | O81: 32.54269 | P81: 8708.0714 | Q81: 0.076579909 | R81: -0.6971775 | S81: =FALSE() -> FALSE
A82: 41718 | B82: 180394.83 | C82: 172344.3 | D82: 5149 | E82: 35.034925 | F82: 33.471413 | G82: 8050.5233 | H82: 0.04462724 | I82: 0.04462724 | J82: 2014 | K82: 3 | L82: 12 | M82: Thursday | N82: =FALSE() -> FALSE | O82: 32.77836 | P82: 8319.3571 | Q82: 0.068843143 | R82: -0.38108199 | S82: =FALSE() -> FALSE
A83: 41719 | B83: 200939.69 | C83: 192019.14 | D83: 5735 | E83: 35.037435 | F83: 33.481978 | G83: 8920.5481 | H83: 0.044394156 | I83: 0.044394156 | J83: 2014 | K83: 3 | L83: 12 | M83: Friday | N83: =FALSE() -> FALSE | O83: 32.917689 | P83: 8324.8571 | Q83: 0.064395374 | R83: -0.31109929 | S83: =FALSE() -> FALSE
A84: 41720 | B84: 172953.92 | C84: 165201.31 | D84: 4936 | E84: 35.039288 | F84: 33.46866 | G84: 7752.6197 | H84: 0.044824769 | I84: 0.044824769 | J84: 2014 | K84: 3 | L84: 12 | M84: Saturday | N84: =TRUE() -> TRUE | O84: 33.13619 | P84: 7695.1429 | Q84: 0.057432624 | R84: -0.35855642 | S84: =FALSE() -> FALSE
A85: 41721 | B85: 70194.8 | C85: 67061.623 | D85: 2003 | E85: 35.044833 | F85: 33.48059 | G85: 3133.1768 | H85: 0.044635455 | I85: 0.044635455 | J85: 2014 | K85: 3 | L85: 12 | M85: Sunday | N85: =TRUE() -> TRUE | O85: 33.354324 | P85: 6886.1429 | Q85: 0.050683352 | R85: -0.70912599 | S85: =FALSE() -> FALSE
A86: 41722 | B86: 81378.215 | C86: 77703.646 | D86: 2323 | E86: 35.031517 | F86: 33.449697 | G86: 3674.5683 | H86: 0.045154201 | I86: 0.045154201 | J86: 2014 | K86: 3 | L86: 13 | M86: Monday | N86: =FALSE() -> FALSE | O86: 33.569253 | P86: 6528.2143 | Q86: 0.043559633 | R86: -0.64415996 | S86: =FALSE() -> FALSE
A87: 41723 | B87: 130227.01 | C87: 127394.29 | D87: 3822 | E87: 34.073002 | F87: 33.331839 | G87: 2832.7255 | H87: 0.021752211 | I87: 0.021752211 | J87: 2014 | K87: 3 | L87: 13 | M87: Tuesday | N87: =FALSE() -> FALSE | O87: 33.782538 | P87: 6056.1429 | Q87: 0.0085980681 | R87: -0.36890524 | S87: =FALSE() -> FALSE
A88: 41724 | B88: 125310.04 | C88: 122275.1 | D88: 3666 | E88: 34.181679 | F88: 33.35382 | G88: 3034.9338 | H88: 0.024219399 | I88: 0.024219399 | J88: 2014 | K88: 3 | L88: 13 | M88: Wednesday | N88: =FALSE() -> FALSE | O88: 33.886298 | P88: 5919.3571 | Q88: 0.0087168449 | R88: -0.38067599 | S88: =FALSE() -> FALSE
A89: 41725 | B89: 119452.34 | C89: 118186.58 | D89: 3543 | E89: 33.715027 | F89: 33.357769 | G89: 1265.7646 | H89: 0.010596399 | I89: 0.010596399 | J89: 2014 | K89: 3 | L89: 13 | M89: Thursday | N89: =FALSE() -> FALSE | O89: 34.008198 | P89: 5759.5714 | Q89: -0.0086205998 | R89: -0.38485006 | S89: =FALSE() -> FALSE
A90: 41726 | B90: 276174.77 | C90: 271550.9 | D90: 8130 | E90: 33.969836 | F90: 33.401094 | G90: 4623.8737 | H90: 0.016742564 | I90: 0.016742564 | J90: 2014 | K90: 3 | L90: 13 | M90: Friday | N90: =FALSE() -> FALSE | O90: 34.090126 | P90: 5651.5 | Q90: -0.0035285781 | R90: 0.43855614 | S90: =FALSE() -> FALSE
A91: 41727 | B91: 357369.27 | C91: 352250.83 | D91: 10518 | E91: 33.976922 | F91: 33.490286 | G91: 5118.4369 | H91: 0.014322543 | I91: 0.014322543 | J91: 2014 | K91: 3 | L91: 13 | M91: Saturday | N91: =TRUE() -> TRUE | O91: 34.192098 | P91: 5363.1429 | Q91: -0.0062931371 | R91: 0.9611635 | S91: =FALSE() -> FALSE
A92: 41728 | B92: 163865.49 | C92: 160525.43 | D92: 4791 | E92: 34.202774 | F92: 33.50562 | G92: 3340.0634 | H92: 0.020382958 | I92: 0.020382958 | J92: 2014 | K92: 3 | L92: 13 | M92: Sunday | N92: =TRUE() -> TRUE | O92: 34.301502 | P92: 4973.6429 | Q92: -0.0028782495 | R92: -0.03672215 | S92: =FALSE() -> FALSE
A93: 41729 | B93: 190719.61 | C93: 187072.6 | D93: 5583 | E93: 34.160776 | F93: 33.50754 | G93: 3647.0193 | H93: 0.019122413 | I93: 0.019122413 | J93: 2014 | K93: 3 | L93: 14 | M93: Monday | N93: =FALSE() -> FALSE | O93: 34.42151 | P93: 4818.1429 | Q93: -0.007574724 | R93: 0.15874522 | S93: =FALSE() -> FALSE
A94: 41730 | B94: 244535.21 | C94: 239700.68 | D94: 7155 | E94: 34.176828 | F94: 33.501144 | G94: 4834.5204 | H94: 0.019770243 | I94: 0.019770243 | J94: 2014 | K94: 4 | L94: 14 | M94: Tuesday | N94: =FALSE() -> FALSE | O94: 34.53868 | P94: 4681.6429 | Q94: -0.010476703 | R94: 0.52830966 | S94: =FALSE() -> FALSE
A95: 41731 | B95: 155620.5 | C95: 153366.02 | D95: 4575 | E95: 34.015411 | F95: 33.522627 | G95: 2254.485 | H95: 0.014487069 | I95: 0.014487069 | J95: 2014 | K95: 4 | L95: 14 | M95: Wednesday | N95: =FALSE() -> FALSE | O95: 34.477118 | P95: 4999.3571 | Q95: -0.013391697 | R95: -0.084882342 | S95: =FALSE() -> FALSE
A96: 41732 | B96: 136001.98 | C96: 134523.07 | D96: 3997 | E96: 34.026014 | F96: 33.656009 | G96: 1478.9095 | H96: 0.010874177 | I96: 0.010874177 | J96: 2014 | K96: 4 | L96: 14 | M96: Thursday | N96: =FALSE() -> FALSE | O96: 34.404304 | P96: 5137.7857 | Q96: -0.010995421 | R96: -0.2220384 | S96: =FALSE() -> FALSE
A97: 41733 | B97: 190559.89 | C97: 187742.3 | D97: 5558 | E97: 34.285694 | F97: 33.778751 | G97: 2817.5875 | H97: 0.014785837 | I97: 0.014785837 | J97: 2014 | K97: 4 | L97: 14 | M97: Friday | N97: =FALSE() -> FALSE | O97: 34.332239 | P97: 5055.5 | Q97: -0.0013557154 | R97: 0.099396697 | S97: =FALSE() -> FALSE
A98: 41734 | B98: 217110.5 | C98: 213540.73 | D98: 6320 | E98: 34.352928 | F98: 33.788091 | G98: 3569.7683 | H98: 0.016442173 | I98: 0.016442173 | J98: 2014 | K98: 4 | L98: 14 | M98: Saturday | N98: =TRUE() -> TRUE | O98: 34.278543 | P98: 5042.8571 | Q98: 0.0021700059 | R98: 0.25325779 | S98: =FALSE() -> FALSE
A99: 41735 | B99: 119190.1 | C99: 116856.31 | D99: 3447 | E99: 34.577923 | F99: 33.900875 | G99: 2333.7854 | H99: 0.019580363 | I99: 0.019580363 | J99: 2014 | K99: 4 | L99: 14 | M99: Sunday | N99: =TRUE() -> TRUE | O99: 34.229517 | P99: 5141.7143 | Q99: 0.010178513 | R99: -0.32960102 | S99: =FALSE() -> FALSE
A100: 41736 | B100: 131910.2 | C100: 130784.44 | D100: 3854 | E100: 34.226829 | F100: 33.934729 | G100: 1125.7527 | H100: 0.0085342359 | I100: 0.0085342359 | J100: 2014 | K100: 4 | L100: 15 | M100: Monday | N100: =FALSE() -> FALSE | O100: 34.196167 | P100: 5244.8571 | Q100: 0.00089665176 | R100: -0.26518494 | S100: =FALSE() -> FALSE
...

Sheet KPI Summary
B2: Sales Case Study — KPI Summary
B3: Metrics 1–4: daily price per unit, average unit price, daily % gross profit, daily % gross profit per unit
B5: Metric | C5: Value | D5: How it is calculated
B6: Date range | C6: =TEXT('Raw Data'!A2,"yyyy-mm-dd") & " to " & TEXT('Raw Data'!A1054,"yyyy-mm-dd") -> 2013-12-30 to 2016-11-16 | D6: Min / max of Raw Data date column
B7: Total days in dataset | C7: =COUNT('Raw Data'!A2:A1054) -> 1053 | D7: COUNT of daily records
B8: Total Sales (R) | C8: =SUM('Raw Data'!B2:B1054) -> 1.8690983e+08 | D8: SUM of daily Sales
B9: Total Cost of Sales (R) | C9: =SUM('Raw Data'!C2:C1054) -> 1.9402611e+08 | D9: SUM of daily Cost of Sales
B10: Total Quantity Sold (units) | C10: =SUM('Raw Data'!D2:D1054) -> 5279872 | D10: SUM of daily Quantity Sold
B11: Total Gross Profit (R) | C11: =SUM('Raw Data'!G2:G1054) -> -7116281.2 | D11: Total Sales − Total Cost of Sales
B12: Overall Gross Profit % | C12: =SUM('Raw Data'!G2:G1054)/SUM('Raw Data'!B2:B1054) -> -0.038073339 | D12: Total Gross Profit / Total Sales
B13: KPI 1 — Daily Sales Price per Unit | C13: =AVERAGE('Raw Data'!E2:E1054) -> 37.072852 | D13: Average of daily Sales÷Quantity (full series in 'Daily Metrics' sheet, Raw Data col E)
B14: KPI 2 — Average Unit Sales Price of Product (simple mean of daily price) | C14: =AVERAGE('Raw Data'!E2:E1054) -> 37.072852 | D14: AVERAGE of the daily price-per-unit column
B15: KPI 2b — Average Unit Sales Price (volume-weighted) | C15: =SUM('Raw Data'!B2:B1054)/SUM('Raw Data'!D2:D1054) -> 35.400447 | D15: Total Sales / Total Quantity Sold (weights by daily volume)
B16: KPI 3 — Average Daily % Gross Profit | C16: =AVERAGE('Raw Data'!H2:H1054) -> -0.0087497665 | D16: Average of daily (Sales−Cost)/Sales (full series in 'Daily Metrics' sheet)
B17: KPI 4 — Average Daily % Gross Profit per Unit | C17: =AVERAGE('Raw Data'!I2:I1054) -> -0.0087497665 | D17: Average of daily (Price/unit−Cost/unit)/Price per unit — mathematically identical to KPI 3
B19: Note: Gross Profit % and Gross Profit % per Unit are mathematically identical ((Sales−Cost)/Sales = (Price−Cost)/Price), confirmed to <1e-10 difference across all 1,053 days.

Sheet Daily Metrics
A1: Daily Metrics (1–4)
A2: Pulled directly from Raw Data via formulas — recalculates if Raw Data changes
A4: Date | B4: Daily Sales Price per Unit (R) | C4: Daily Cost per Unit (R) | D4: Daily % Gross Profit | E4: Daily % Gross Profit per Unit | F4: On Promotion?
A5: ='Raw Data'!A2 -> 41638 | B5: ='Raw Data'!E2 -> 32.801812 | C5: ='Raw Data'!F2 -> 33.701424 | D5: ='Raw Data'!H2 -> -0.027425689 | E5: ='Raw Data'!I2 -> -0.027425689 | F5: ='Raw Data'!S2 -> FALSE
A6: ='Raw Data'!A3 -> 41639 | B6: ='Raw Data'!E3 -> 32.40672 | C6: ='Raw Data'!F3 -> 33.123233 | D6: ='Raw Data'!H3 -> -0.022109991 | E6: ='Raw Data'!I3 -> -0.022109991 | F6: ='Raw Data'!S3 -> FALSE
A7: ='Raw Data'!A4 -> 41640 | B7: ='Raw Data'!E4 -> 32.405701 | C7: ='Raw Data'!F4 -> 32.855235 | D7: ='Raw Data'!H4 -> -0.013872047 | E7: ='Raw Data'!I4 -> -0.013872047 | F7: ='Raw Data'!S4 -> FALSE
A8: ='Raw Data'!A5 -> 41641 | B8: ='Raw Data'!E5 -> 32.416699 | C8: ='Raw Data'!F5 -> 32.855251 | D8: ='Raw Data'!H5 -> -0.013528595 | E8: ='Raw Data'!I5 -> -0.013528595 | F8: ='Raw Data'!S5 -> FALSE
A9: ='Raw Data'!A6 -> 41642 | B9: ='Raw Data'!E6 -> 32.418294 | C9: ='Raw Data'!F6 -> 33.102568 | D9: ='Raw Data'!H6 -> -0.021107646 | E9: ='Raw Data'!I6 -> -0.021107646 | F9: ='Raw Data'!S6 -> FALSE
A10: ='Raw Data'!A7 -> 41643 | B10: ='Raw Data'!E7 -> 32.422802 | C10: ='Raw Data'!F7 -> 33.120628 | D10: ='Raw Data'!H7 -> -0.021522695 | E10: ='Raw Data'!I7 -> -0.021522695 | F10: ='Raw Data'!S7 -> FALSE
A11: ='Raw Data'!A8 -> 41644 | B11: ='Raw Data'!E8 -> 32.438248 | C11: ='Raw Data'!F8 -> 33.143245 | D11: ='Raw Data'!H8 -> -0.021733494 | E11: ='Raw Data'!I8 -> -0.021733494 | F11: ='Raw Data'!S8 -> FALSE
A12: ='Raw Data'!A9 -> 41645 | B12: ='Raw Data'!E9 -> 32.425058 | C12: ='Raw Data'!F9 -> 33.175917 | D12: ='Raw Data'!H9 -> -0.023156756 | E12: ='Raw Data'!I9 -> -0.023156756 | F12: ='Raw Data'!S9 -> FALSE
A13: ='Raw Data'!A10 -> 41646 | B13: ='Raw Data'!E10 -> 32.41505 | C13: ='Raw Data'!F10 -> 33.212845 | D13: ='Raw Data'!H10 -> -0.024611881 | E13: ='Raw Data'!I10 -> -0.024611881 | F13: ='Raw Data'!S10 -> FALSE
A14: ='Raw Data'!A11 -> 41647 | B14: ='Raw Data'!E11 -> 34.058997 | C14: ='Raw Data'!F11 -> 33.238116 | D14: ='Raw Data'!H11 -> 0.024101742 | E14: ='Raw Data'!I11 -> 0.024101742 | F14: ='Raw Data'!S11 -> FALSE
A15: ='Raw Data'!A12 -> 41648 | B15: ='Raw Data'!E12 -> 34.126086 | C15: ='Raw Data'!F12 -> 33.180265 | D15: ='Raw Data'!H12 -> 0.027715465 | E15: ='Raw Data'!I12 -> 0.027715465 | F15: ='Raw Data'!S12 -> FALSE
A16: ='Raw Data'!A13 -> 41649 | B16: ='Raw Data'!E13 -> 34.10974 | C16: ='Raw Data'!F13 -> 33.286386 | D16: ='Raw Data'!H13 -> 0.024138379 | E16: ='Raw Data'!I13 -> 0.024138379 | F16: ='Raw Data'!S13 -> FALSE
... A1057: ='Raw Data'!A1054 -> 42690 | B1057: ='Raw Data'!E1054 -> 43.805997 | C1057: ='Raw Data'!F1054 -> 40.515525 | D1057: ='Raw Data'!H1054 -> 0.075114645 | E1057: ='Raw Data'!I1054 -> 0.075114645 | F1057: ='Raw Data'!S1054 -> FALSE

Sheet Pivot - Monthly
A1: Monthly Sales Pivot
A2: Built with SUMIFS / AVERAGEIFS against Raw Data (year, month columns)
A4: Year-Month | B4: Total Sales (R) | C4: Total Quantity | D4: Total Gross Profit (R) | E4: Gross Profit % | F4: Avg Price per Unit (R)
A5: 2013-12 | B5: =SUMIFS('Raw Data'!$B$2:$B$1054,'Raw Data'!$J$2:$J$1054,2013,'Raw Data'!$K$2:$K$1054,12) -> 524283.45 | C5: =SUMIFS('Raw Data'!$D$2:$D$1054,'Raw Data'!$J$2:$J$1054,2013,'Raw Data'!$K$2:$K$1054,12) -> 16095 | D5: =SUMIFS('Raw Data'!$G$2:$G$1054,'Raw Data'!$J$2:$J$1054,2013,'Raw Data'!$K$2:$K$1054,12) -> -12782.289 | E5: =D5/B5 -> -0.024380493 | F5: =AVERAGEIFS('Raw Data'!$E$2:$E$1054,'Raw Data'!$J$2:$J$1054,2013,'Raw Data'!$K$2:$K$1054,12) -> 32.604266
A6: 2014-01 | B6: =SUMIFS('Raw Data'!$B$2:$B$1054,'Raw Data'!$J$2:$J$1054,2014,'Raw Data'!$K$2:$K$1054,1) -> 4008180.5 | C6: =SUMIFS('Raw Data'!$D$2:$D$1054,'Raw Data'!$J$2:$J$1054,2014,'Raw Data'!$K$2:$K$1054,1) -> 119965 | D6: =SUMIFS('Raw Data'!$G$2:$G$1054,'Raw Data'!$J$2:$J$1054,2014,'Raw Data'!$K$2:$K$1054,1) -> 12460.645 | E6: =D6/B6 -> 0.0031088035 | F6: =AVERAGEIFS('Raw Data'!$E$2:$E$1054,'Raw Data'!$J$2:$J$1054,2014,'Raw Data'!$K$2:$K$1054,1) -> 33.739264
A7: 2014-02 | B7: =SUMIFS('Raw Data'!$B$2:$B$1054,'Raw Data'!$J$2:$J$1054,2014,'Raw Data'!$K$2:$K$1054,2) -> 5780487.2 | C7: =SUMIFS('Raw Data'!$D$2:$D$1054,'Raw Data'!$J$2:$J$1054,2014,'Raw Data'!$K$2:$K$1054,2) -> 178035 | D7: =SUMIFS('Raw Data'!$G$2:$G$1054,'Raw Data'!$J$2:$J$1054,2014,'Raw Data'!$K$2:$K$1054,2) -> -132991.39 | E7: =D7/B7 -> -0.023006951 | F7: =AVERAGEIFS('Raw Data'!$E$2:$E$1054,'Raw Data'!$J$2:$J$1054,2014,'Raw Data'!$K$2:$K$1054,2) -> 32.766452
A8: 2014-03 | B8: =SUMIFS('Raw Data'!$B$2:$B$1054,'Raw Data'!$J$2:$J$1054,2014,'Raw Data'!$K$2:$K$1054,3) -> 8279517.2 | C8: =SUMIFS('Raw Data'!$D$2:$D$1054,'Raw Data'!$J$2:$J$1054,2014,'Raw Data'!$K$2:$K$1054,3) -> 252836 | D8: =SUMIFS('Raw Data'!$G$2:$G$1054,'Raw Data'!$J$2:$J$1054,2014,'Raw Data'!$K$2:$K$1054,3) -> -136136.84 | E8: =D8/B8 -> -0.016442607 | F8: =AVERAGEIFS('Raw Data'!$E$2:$E$1054,'Raw Data'!$J$2:$J$1054,2014,'Raw Data'!$K$2:$K$1054,3) -> 33.280478
A9: 2014-04 | B9: =SUMIFS('Raw Data'!$B$2:$B$1054,'Raw Data'!$J$2:$J$1054,2014,'Raw Data'!$K$2:$K$1054,4) -> 6435743.3 | C9: =SUMIFS('Raw Data'!$D$2:$D$1054,'Raw Data'!$J$2:$J$1054,2014,'Raw Data'!$K$2:$K$1054,4) -> 190091 | D9: =SUMIFS('Raw Data'!$G$2:$G$1054,'Raw Data'!$J$2:$J$1054,2014,'Raw Data'!$K$2:$K$1054,4) -> -43900.351 | E9: =D9/B9 -> -0.0068213335 | F9: =AVERAGEIFS('Raw Data'!$E$2:$E$1054,'Raw Data'!$J$2:$J$1054,2014,'Raw Data'!$K$2:$K$1054,4) -> 34.062178
A10: 2014-05 | B10: =SUMIFS('Raw Data'!$B$2:$B$1054,'Raw Data'!$J$2:$J$1054,2014,'Raw Data'!$K$2:$K$1054,5) -> 7694906.2 | C10: =SUMIFS('Raw Data'!$D$2:$D$1054,'Raw Data'!$J$2:$J$1054,2014,'Raw Data'!$K$2:$K$1054,5) -> 235793 | D10: =SUMIFS('Raw Data'!$G$2:$G$1054,'Raw Data'!$J$2:$J$1054,2014,'Raw Data'!$K$2:$K$1054,5) -> -322334.26 | E10: =D10/B10 -> -0.041889304 | F10: =AVERAGEIFS('Raw Data'!$E$2:$E$1054,'Raw Data'!$J$2:$J$1054,2014,'Raw Data'!$K$2:$K$1054,5) -> 33.114192
A11: 2014-06 | B11: =SUMIFS('Raw Data'!$B$2:$B$1054,'Raw Data'!$J$2:$J$1054,2014,'Raw Data'!$K$2:$K$1054,6) -> 6456943.6 | C11: =SUMIFS('Raw Data'!$D$2:$D$1054,'Raw Data'!$J$2:$J$1054,2014,'Raw Data'!$K$2:$K$1054,6) -> 198857 | D11: =SUMIFS('Raw Data'!$G$2:$G$1054,'Raw Data'!$J$2:$J$1054,2014,'Raw Data'!$K$2:$K$1054,6) -> -188900.01 | E11: =D11/B11 -> -0.029255329 | F11: =AVERAGEIFS('Raw Data'!$E$2:$E$1054,'Raw Data'!$J$2:$J$1054,2014,'Raw Data'!$K$2:$K$1054,6) -> 32.943879
A12: 2014-07 | B12: =SUMIFS('Raw Data'!$B$2:$B$1054,'Raw Data'!$J$2:$J$1054,2014,'Raw Data'!$K$2:$K$1054,7) -> 4933710.8 | C12: =SUMIFS('Raw Data'!$D$2:$D$1054,'Raw Data'!$J$2:$J$1054,2014,'Raw Data'!$K$2:$K$1054,7) -> 147449 | D12: =SUMIFS('Raw Data'!$G$2:$G$1054,'Raw Data'!$J$2:$J$1054,2014,'Raw Data'!$K$2:$K$1054,7) -> -71184.101 | E12: =D12/B12 -> -0.014428106 | F12: =AVERAGEIFS('Raw Data'!$E$2:$E$1054,'Raw Data'!$J$2:$J$1054,2014,'Raw Data'!$K$2:$K$1054,7) -> 34.201254
A13: 2014-08 | B13: =SUMIFS('Raw Data'!$B$2:$B$1054,'Raw Data'!$J$2:$J$1054,2014,'Raw Data'!$K$2:$K$1054,8) -> 10010378 | C13: =SUMIFS('Raw Data'!$D$2:$D$1054,'Raw Data'!$J$2:$J$1054,2014,'Raw Data'!$K$2:$K$1054,8) -> 310572 | D13: =SUMIFS('Raw Data'!$G$2:$G$1054,'Raw Data'!$J$2:$J$1054,2014,'Raw Data'!$K$2:$K$1054,8) -> -514054.14 | E13: =D13/B13 -> -0.051352119 | F13: =AVERAGEIFS('Raw Data'!$E$2:$E$1054,'Raw Data'!$J$2:$J$1054,2014,'Raw Data'!$K$2:$K$1054,8) -> 32.495681
A14: 2014-09 | B14: =SUMIFS('Raw Data'!$B$2:$B$1054,'Raw Data'!$J$2:$J$1054,2014,'Raw Data'!$K$2:$K$1054,9) -> 7643452.7 | C14: =SUMIFS('Raw Data'!$D$2:$D$1054,'Raw Data'!$J$2:$J$1054,2014,'Raw Data'!$K$2:$K$1054,9) -> 237742 | D14: =SUMIFS('Raw Data'!$G$2:$G$1054,'Raw Data'!$J$2:$J$1054,2014,'Raw Data'!$K$2:$K$1054,9) -> -550107.35 | E14: =D14/B14 -> -0.071971055 | F14: =AVERAGEIFS('Raw Data'!$E$2:$E$1054,'Raw Data'!$J$2:$J$1054,2014,'Raw Data'!$K$2:$K$1054,9) -> 33.285362
A15: 2014-10 | B15: =SUMIFS('Raw Data'!$B$2:$B$1054,'Raw Data'!$J$2:$J$1054,2014,'Raw Data'!$K$2:$K$1054,10) -> 5924683.4 | C15: =SUMIFS('Raw Data'!$D$2:$D$1054,'Raw Data'!$J$2:$J$1054,2014,'Raw Data'!$K$2:$K$1054,10) -> 171709 | D15: =SUMIFS('Raw Data'!$G$2:$G$1054,'Raw Data'!$J$2:$J$1054,2014,'Raw Data'!$K$2:$K$1054,10) -> -113777.94 | E15: =D15/B15 -> -0.019204053 | F15: =AVERAGEIFS('Raw Data'!$E$2:$E$1054,'Raw Data'!$J$2:$J$1054,2014,'Raw Data'!$K$2:$K$1054,10) -> 35.905736
A16: 2014-11 | B16: =SUMIFS('Raw Data'!$B$2:$B$1054,'Raw Data'!$J$2:$J$1054,2014,'Raw Data'!$K$2:$K$1054,11) -> 2631353.3 | C16: =SUMIFS('Raw Data'!$D$2:$D$1054,'Raw Data'!$J$2:$J$1054,2014,'Raw Data'!$K$2:$K$1054,11) -> 68569 | D16: =SUMIFS('Raw Data'!$G$2:$G$1054,'Raw Data'!$J$2:$J$1054,2014,'Raw Data'!$K$2:$K$1054,11) -> 114228.51 | E16: =D16/B16 -> 0.043410554 | F16: =AVERAGEIFS('Raw Data'!$E$2:$E$1054,'Raw Data'!$J$2:$J$1054,2014,'Raw Data'!$K$2:$K$1054,11) -> 39.257755
A17: 2014-12 | B17: =SUMIFS('Raw Data'!$B$2:$B$1054,'Raw Data'!$J$2:$J$1054,2014,'Raw Data'!$K$2:$K$1054,12) -> 5615619.3 | C17: =SUMIFS('Raw Data'!$D$2:$D$1054,'Raw Data'!$J$2:$J$1054,2014,'Raw Data'!$K$2:$K$1054,12) -> 142612 | D17: =SUMIFS('Raw Data'!$G$2:$G$1054,'Raw Data'!$J$2:$J$1054,2014,'Raw Data'!$K$2:$K$1054,12) -> -319176.76 | E17: =D17/B17 -> -0.056837322 | F17: =AVERAGEIFS('Raw Data'!$E$2:$E$1054,'Raw Data'!$J$2:$J$1054,2014,'Raw Data'!$K$2:$K$1054,12) -> 39.695771
A18: 2015-01 | B18: =SUMIFS('Raw Data'!$B$2:$B$1054,'Raw Data'!$J$2:$J$1054,2015,'Raw Data'!$K$2:$K$1054,1) -> 3696191.5 | C18: =SUMIFS('Raw Data'!$D$2:$D$1054,'Raw Data'!$J$2:$J$1054,2015,'Raw Data'!$K$2:$K$1054,1) -> 91740 | D18: =SUMIFS('Raw Data'!$G$2:$G$1054,'Raw Data'!$J$2:$J$1054,2015,'Raw Data'!$K$2:$K$1054,1) -> -155068.96 | E18: =D18/B18 -> -0.041953713 | F18: =AVERAGEIFS('Raw Data'!$E$2:$E$1054,'Raw Data'!$J$2:$J$1054,2015,'Raw Data'!$K$2:$K$1054,1) -> 40.673899
A19: 2015-02 | B19: =SUMIFS('Raw Data'!$B$2:$B$1054,'Raw Data'!$J$2:$J$1054,2015,'Raw Data'!$K$2:$K$1054,2) -> 4901504.9 | C19: =SUMIFS('Raw Data'!$D$2:$D$1054,'Raw Data'!$J$2:$J$1054,2015,'Raw Data'!$K$2:$K$1054,2) -> 127753 | D19: =SUMIFS('Raw Data'!$G$2:$G$1054,'Raw Data'!$J$2:$J$1054,2015,'Raw Data'!$K$2:$K$1054,2) -> -250251.37 | E19: =D19/B19 -> -0.051056029 | F19: =AVERAGEIFS('Raw Data'!$E$2:$E$1054,'Raw Data'!$J$2:$J$1054,2015,'Raw Data'!$K$2:$K$1054,2) -> 38.922637
A20: 2015-03 | B20: =SUMIFS('Raw Data'!$B$2:$B$1054,'Raw Data'!$J$2:$J$1054,2015,'Raw Data'!$K$2:$K$1054,3) -> 5269353.2 | C20: =SUMIFS('Raw Data'!$D$2:$D$1054,'Raw Data'!$J$2:$J$1054,2015,'Raw Data'!$K$2:$K$1054,3) -> 136673 | D20: =SUMIFS('Raw Data'!$G$2:$G$1054,'Raw Data'!$J$2:$J$1054,2015,'Raw Data'!$K$2:$K$1054,3) -> -330277.57 | E20: =D20/B20 -> -0.062678958 | F20: =AVERAGEIFS('Raw Data'!$E$2:$E$1054,'Raw Data'!$J$2:$J$1054,2015,'Raw Data'!$K$2:$K$1054,3) -> 39.514039
A21: 2015-04 | B21: =SUMIFS('Raw Data'!$B$2:$B$1054,'Raw Data'!$J$2:$J$1054,2015,'Raw Data'!$K$2:$K$1054,4) -> 5963994 | C21: =SUMIFS('Raw Data'!$D$2:$D$1054,'Raw Data'!$J$2:$J$1054,2015,'Raw Data'!$K$2:$K$1054,4) -> 153702 | D21: =SUMIFS('Raw Data'!$G$2:$G$1054,'Raw Data'!$J$2:$J$1054,2015,'Raw Data'!$K$2:$K$1054,4) -> -322679.7 | E21: =D21/B21 -> -0.054104632 | F21: =AVERAGEIFS('Raw Data'!$E$2:$E$1054,'Raw Data'!$J$2:$J$1054,2015,'Raw Data'!$K$2:$K$1054,4) -> 39.977304
A22: 2015-05 | B22: =SUMIFS('Raw Data'!$B$2:$B$1054,'Raw Data'!$J$2:$J$1054,2015,'Raw Data'!$K$2:$K$1054,5) -> 8384367.2 | C22: =SUMIFS('Raw Data'!$D$2:$D$1054,'Raw Data'!$J$2:$J$1054,2015,'Raw Data'!$K$2:$K$1054,5) -> 220775 | D22: =SUMIFS('Raw Data'!$G$2:$G$1054,'Raw Data'!$J$2:$J$1054,2015,'Raw Data'!$K$2:$K$1054,5) -> -589334.66 | E22: =D22/B22 -> -0.0702897 | F22: =AVERAGEIFS('Raw Data'!$E$2:$E$1054,'Raw Data'!$J$2:$J$1054,2015,'Raw Data'!$K$2:$K$1054,5) -> 38.12341
A23: 2015-06 | B23: =SUMIFS('Raw Data'!$B$2:$B$1054,'Raw Data'!$J$2:$J$1054,2015,'Raw Data'!$K$2:$K$1054,6) -> 5332108.3 | C23: =SUMIFS('Raw Data'!$D$2:$D$1054,'Raw Data'!$J$2:$J$1054,2015,'Raw Data'!$K$2:$K$1054,6) -> 136581 | D23: =SUMIFS('Raw Data'!$G$2:$G$1054,'Raw Data'!$J$2:$J$1054,2015,'Raw Data'!$K$2:$K$1054,6) -> -188817.05 | E23: =D23/B23 -> -0.03541133 | F23: =AVERAGEIFS('Raw Data'!$E$2:$E$1054,'Raw Data'!$J$2:$J$1054,2015,'Raw Data'!$K$2:$K$1054,6) -> 40.037434
A24: 2015-07 | B24: =SUMIFS('Raw Data'!$B$2:$B$1054,'Raw Data'!$J$2:$J$1054,2015,'Raw Data'!$K$2:$K$1054,7) -> 3677692.4 | C24: =SUMIFS('Raw Data'!$D$2:$D$1054,'Raw Data'!$J$2:$J$1054,2015,'Raw Data'!$K$2:$K$1054,7) -> 95600 | D24: =SUMIFS('Raw Data'!$G$2:$G$1054,'Raw Data'!$J$2:$J$1054,2015,'Raw Data'!$K$2:$K$1054,7) -> -151496.17 | E24: =D24/B24 -> -0.041193269 | F24: =AVERAGEIFS('Raw Data'!$E$2:$E$1054,'Raw Data'!$J$2:$J$1054,2015,'Raw Data'!$K$2:$K$1054,7) -> 38.735437
A25: 2015-08 | B25: =SUMIFS('Raw Data'!$B$2:$B$1054,'Raw Data'!$J$2:$J$1054,2015,'Raw Data'!$K$2:$K$1054,8) -> 3934668.4 | C25: =SUMIFS('Raw Data'!$D$2:$D$1054,'Raw Data'!$J$2:$J$1054,2015,'Raw Data'!$K$2:$K$1054,8) -> 108899 | D25: =SUMIFS('Raw Data'!$G$2:$G$1054,'Raw Data'!$J$2:$J$1054,2015,'Raw Data'!$K$2:$K$1054,8) -> -276258.93 | E25: =D25/B25 -> -0.070211489 | F25: =AVERAGEIFS('Raw Data'!$E$2:$E$1054,'Raw Data'!$J$2:$J$1054,2015,'Raw Data'!$K$2:$K$1054,8) -> 37.575361
A26: 2015-09 | B26: =SUMIFS('Raw Data'!$B$2:$B$1054,'Raw Data'!$J$2:$J$1054,2015,'Raw Data'!$K$2:$K$1054,9) -> 4669899.9 | C26: =SUMIFS('Raw Data'!$D$2:$D$1054,'Raw Data'!$J$2:$J$1054,2015,'Raw Data'!$K$2:$K$1054,9) -> 134837 | D26: =SUMIFS('Raw Data'!$G$2:$G$1054,'Raw Data'!$J$2:$J$1054,2015,'Raw Data'!$K$2:$K$1054,9) -> -354594.84 | E26: =D26/B26 -> -0.075932 | F26: =AVERAGEIFS('Raw Data'!$E$2:$E$1054,'Raw Data'!$J$2:$J$1054,2015,'Raw Data'!$K$2:$K$1054,9) -> 36.454853
A27: 2015-10 | B27: =SUMIFS('Raw Data'!$B$2:$B$1054,'Raw Data'!$J$2:$J$1054,2015,'Raw Data'!$K$2:$K$1054,10) -> 4828975.1 | C27: =SUMIFS('Raw Data'!$D$2:$D$1054,'Raw Data'!$J$2:$J$1054,2015,'Raw Data'!$K$2:$K$1054,10) -> 135328 | D27: =SUMIFS('Raw Data'!$G$2:$G$1054,'Raw Data'!$J$2:$J$1054,2015,'Raw Data'!$K$2:$K$1054,10) -> -346519 | E27: =D27/B27 -> -0.071758291 | F27: =AVERAGEIFS('Raw Data'!$E$2:$E$1054,'Raw Data'!$J$2:$J$1054,2015,'Raw Data'!$K$2:$K$1054,10) -> 37.399806
A28: 2015-11 | B28: =SUMIFS('Raw Data'!$B$2:$B$1054,'Raw Data'!$J$2:$J$1054,2015,'Raw Data'!$K$2:$K$1054,11) -> 6538148.9 | C28: =SUMIFS('Raw Data'!$D$2:$D$1054,'Raw Data'!$J$2:$J$1054,2015,'Raw Data'!$K$2:$K$1054,11) -> 185868 | D28: =SUMIFS('Raw Data'!$G$2:$G$1054,'Raw Data'!$J$2:$J$1054,2015,'Raw Data'!$K$2:$K$1054,11) -> -600684.57 | E28: =D28/B28 -> -0.091873798 | F28: =AVERAGEIFS('Raw Data'!$E$2:$E$1054,'Raw Data'!$J$2:$J$1054,2015,'Raw Data'!$K$2:$K$1054,11) -> 35.609829
A29: 2015-12 | B29: =SUMIFS('Raw Data'!$B$2:$B$1054,'Raw Data'!$J$2:$J$1054,2015,'Raw Data'!$K$2:$K$1054,12) -> 6820689.7 | C29: =SUMIFS('Raw Data'!$D$2:$D$1054,'Raw Data'!$J$2:$J$1054,2015,'Raw Data'!$K$2:$K$1054,12) -> 187333 | D29: =SUMIFS('Raw Data'!$G$2:$G$1054,'Raw Data'!$J$2:$J$1054,2015,'Raw Data'!$K$2:$K$1054,12) -> -333627.64 | E29: =D29/B29 -> -0.048914063 | F29: =AVERAGEIFS('Raw Data'!$E$2:$E$1054,'Raw Data'!$J$2:$J$1054,2015,'Raw Data'!$K$2:$K$1054,12) -> 36.923677
A30: 2016-01 | B30: =SUMIFS('Raw Data'!$B$2:$B$1054,'Raw Data'!$J$2:$J$1054,2016,'Raw Data'!$K$2:$K$1054,1) -> 5403090.5 | C30: =SUMIFS('Raw Data'!$D$2:$D$1054,'Raw Data'!$J$2:$J$1054,2016,'Raw Data'!$K$2:$K$1054,1) -> 150561 | D30: =SUMIFS('Raw Data'!$G$2:$G$1054,'Raw Data'!$J$2:$J$1054,2016,'Raw Data'!$K$2:$K$1054,1) -> -254252.21 | E30: =D30/B30 -> -0.04705681 | F30: =AVERAGEIFS('Raw Data'!$E$2:$E$1054,'Raw Data'!$J$2:$J$1054,2016,'Raw Data'!$K$2:$K$1054,1) -> 37.60274
A31: 2016-02 | B31: =SUMIFS('Raw Data'!$B$2:$B$1054,'Raw Data'!$J$2:$J$1054,2016,'Raw Data'!$K$2:$K$1054,2) -> 4891882.3 | C31: =SUMIFS('Raw Data'!$D$2:$D$1054,'Raw Data'!$J$2:$J$1054,2016,'Raw Data'!$K$2:$K$1054,2) -> 132990 | D31: =SUMIFS('Raw Data'!$G$2:$G$1054,'Raw Data'!$J$2:$J$1054,2016,'Raw Data'!$K$2:$K$1054,2) -> 2578.6644 | E31: =D31/B31 -> 0.00052713133 | F31: =AVERAGEIFS('Raw Data'!$E$2:$E$1054,'Raw Data'!$J$2:$J$1054,2016,'Raw Data'!$K$2:$K$1054,2) -> 38.49059
A32: 2016-03 | B32: =SUMIFS('Raw Data'!$B$2:$B$1054,'Raw Data'!$J$2:$J$1054,2016,'Raw Data'!$K$2:$K$1054,3) -> 2951856 | C32: =SUMIFS('Raw Data'!$D$2:$D$1054,'Raw Data'!$J$2:$J$1054,2016,'Raw Data'!$K$2:$K$1054,3) -> 74185 | D32: =SUMIFS('Raw Data'!$G$2:$G$1054,'Raw Data'!$J$2:$J$1054,2016,'Raw Data'!$K$2:$K$1054,3) -> 34054.514 | E32: =D32/B32 -> 0.011536645 | F32: =AVERAGEIFS('Raw Data'!$E$2:$E$1054,'Raw Data'!$J$2:$J$1054,2016,'Raw Data'!$K$2:$K$1054,3) -> 40.3441
A33: 2016-04 | B33: =SUMIFS('Raw Data'!$B$2:$B$1054,'Raw Data'!$J$2:$J$1054,2016,'Raw Data'!$K$2:$K$1054,4) -> 6656880.2 | C33: =SUMIFS('Raw Data'!$D$2:$D$1054,'Raw Data'!$J$2:$J$1054,2016,'Raw Data'!$K$2:$K$1054,4) -> 190235 | D33: =SUMIFS('Raw Data'!$G$2:$G$1054,'Raw Data'!$J$2:$J$1054,2016,'Raw Data'!$K$2:$K$1054,4) -> -470851.73 | E33: =D33/B33 -> -0.070731591 | F33: =AVERAGEIFS('Raw Data'!$E$2:$E$1054,'Raw Data'!$J$2:$J$1054,2016,'Raw Data'!$K$2:$K$1054,4) -> 35.564621
A34: 2016-05 | B34: =SUMIFS('Raw Data'!$B$2:$B$1054,'Raw Data'!$J$2:$J$1054,2016,'Raw Data'!$K$2:$K$1054,5) -> 5170231.9 | C34: =SUMIFS('Raw Data'!$D$2:$D$1054,'Raw Data'!$J$2:$J$1054,2016,'Raw Data'!$K$2:$K$1054,5) -> 146298 | D34: =SUMIFS('Raw Data'!$G$2:$G$1054,'Raw Data'!$J$2:$J$1054,2016,'Raw Data'!$K$2:$K$1054,5) -> -168162.78 | E34: =D34/B34 -> -0.032525191 | F34: =AVERAGEIFS('Raw Data'!$E$2:$E$1054,'Raw Data'!$J$2:$J$1054,2016,'Raw Data'!$K$2:$K$1054,5) -> 38.039882
A35: 2016-06 | B35: =SUMIFS('Raw Data'!$B$2:$B$1054,'Raw Data'!$J$2:$J$1054,2016,'Raw Data'!$K$2:$K$1054,6) -> 6771134.9 | C35: =SUMIFS('Raw Data'!$D$2:$D$1054,'Raw Data'!$J$2:$J$1054,2016,'Raw Data'!$K$2:$K$1054,6) -> 197469 | D35: =SUMIFS('Raw Data'!$G$2:$G$1054,'Raw Data'!$J$2:$J$1054,2016,'Raw Data'!$K$2:$K$1054,6) -> -397214.69 | E35: =D35/B35 -> -0.058662942 | F35: =AVERAGEIFS('Raw Data'!$E$2:$E$1054,'Raw Data'!$J$2:$J$1054,2016,'Raw Data'!$K$2:$K$1054,6) -> 34.827885
A36: 2016-07 | B36: =SUMIFS('Raw Data'!$B$2:$B$1054,'Raw Data'!$J$2:$J$1054,2016,'Raw Data'!$K$2:$K$1054,7) -> 3324825.4 | C36: =SUMIFS('Raw Data'!$D$2:$D$1054,'Raw Data'!$J$2:$J$1054,2016,'Raw Data'!$K$2:$K$1054,7) -> 90653 | D36: =SUMIFS('Raw Data'!$G$2:$G$1054,'Raw Data'!$J$2:$J$1054,2016,'Raw Data'!$K$2:$K$1054,7) -> 56428.159 | E36: =D36/B36 -> 0.016971766 | F36: =AVERAGEIFS('Raw Data'!$E$2:$E$1054,'Raw Data'!$J$2:$J$1054,2016,'Raw Data'!$K$2:$K$1054,7) -> 40.38447
A37: 2016-08 | B37: =SUMIFS('Raw Data'!$B$2:$B$1054,'Raw Data'!$J$2:$J$1054,2016,'Raw Data'!$K$2:$K$1054,8) -> 4343329.4 | C37: =SUMIFS('Raw Data'!$D$2:$D$1054,'Raw Data'!$J$2:$J$1054,2016,'Raw Data'!$K$2:$K$1054,8) -> 123621 | D37: =SUMIFS('Raw Data'!$G$2:$G$1054,'Raw Data'!$J$2:$J$1054,2016,'Raw Data'!$K$2:$K$1054,8) -> -136458.24 | E37: =D37/B37 -> -0.031417889 | F37: =AVERAGEIFS('Raw Data'!$E$2:$E$1054,'Raw Data'!$J$2:$J$1054,2016,'Raw Data'!$K$2:$K$1054,8) -> 36.878844
A38: 2016-09 | B38: =SUMIFS('Raw Data'!$B$2:$B$1054,'Raw Data'!$J$2:$J$1054,2016,'Raw Data'!$K$2:$K$1054,9) -> 3259542.5 | C38: =SUMIFS('Raw Data'!$D$2:$D$1054,'Raw Data'!$J$2:$J$1054,2016,'Raw Data'!$K$2:$K$1054,9) -> 88672 | D38: =SUMIFS('Raw Data'!$G$2:$G$1054,'Raw Data'!$J$2:$J$1054,2016,'Raw Data'!$K$2:$K$1054,9) -> 49345.214 | E38: =D38/B38 -> 0.015138693 | F38: =AVERAGEIFS('Raw Data'!$E$2:$E$1054,'Raw Data'!$J$2:$J$1054,2016,'Raw Data'!$K$2:$K$1054,9) -> 38.892587
A39: 2016-10 | B39: =SUMIFS('Raw Data'!$B$2:$B$1054,'Raw Data'!$J$2:$J$1054,2016,'Raw Data'!$K$2:$K$1054,10) -> 2329172.7 | C39: =SUMIFS('Raw Data'!$D$2:$D$1054,'Raw Data'!$J$2:$J$1054,2016,'Raw Data'!$K$2:$K$1054,10) -> 56667 | D39: =SUMIFS('Raw Data'!$G$2:$G$1054,'Raw Data'!$J$2:$J$1054,2016,'Raw Data'!$K$2:$K$1054,10) -> 219961.64 | E39: =D39/B39 -> 0.094437671 | F39: =AVERAGEIFS('Raw Data'!$E$2:$E$1054,'Raw Data'!$J$2:$J$1054,2016,'Raw Data'!$K$2:$K$1054,10) -> 41.627311
A40: 2016-11 | B40: =SUMIFS('Raw Data'!$B$2:$B$1054,'Raw Data'!$J$2:$J$1054,2016,'Raw Data'!$K$2:$K$1054,11) -> 1851029.9 | C40: =SUMIFS('Raw Data'!$D$2:$D$1054,'Raw Data'!$J$2:$J$1054,2016,'Raw Data'!$K$2:$K$1054,11) -> 43107 | D40: =SUMIFS('Raw Data'!$G$2:$G$1054,'Raw Data'!$J$2:$J$1054,2016,'Raw Data'!$K$2:$K$1054,11) -> 126556.98 | E40: =D40/B40 -> 0.06837112 | F40: =AVERAGEIFS('Raw Data'!$E$2:$E$1054,'Raw Data'!$J$2:$J$1054,2016,'Raw Data'!$K$2:$K$1054,11) -> 42.978499

Sheet Pivot - Yearly
A1: Yearly Sales Pivot
A2: Note: 2013 and 2016 are partial years (2 days and 11 months of data respectively)
A4: Year | B4: Total Sales (R) | C4: Total Quantity | D4: Total Gross Profit (R) | E4: Gross Profit % | F4: Avg Price per Unit (R)
A5: 2013 | B5: =SUMIFS('Raw Data'!$B$2:$B$1054,'Raw Data'!$J$2:$J$1054,2013) -> 524283.45 | C5: =SUMIFS('Raw Data'!$D$2:$D$1054,'Raw Data'!$J$2:$J$1054,2013) -> 16095 | D5: =SUMIFS('Raw Data'!$G$2:$G$1054,'Raw Data'!$J$2:$J$1054,2013) -> -12782.289 | E5: =D5/B5 -> -0.024380493 | F5: =AVERAGEIFS('Raw Data'!$E$2:$E$1054,'Raw Data'!$J$2:$J$1054,2013) -> 32.604266
A6: 2014 | B6: =SUMIFS('Raw Data'!$B$2:$B$1054,'Raw Data'!$J$2:$J$1054,2014) -> 75414976 | C6: =SUMIFS('Raw Data'!$D$2:$D$1054,'Raw Data'!$J$2:$J$1054,2014) -> 2254230 | D6: =SUMIFS('Raw Data'!$G$2:$G$1054,'Raw Data'!$J$2:$J$1054,2014) -> -2265874 | E6: =D6/B6 -> -0.030045412 | F6: =AVERAGEIFS('Raw Data'!$E$2:$E$1054,'Raw Data'!$J$2:$J$1054,2014) -> 34.573533
A7: 2015 | B7: =SUMIFS('Raw Data'!$B$2:$B$1054,'Raw Data'!$J$2:$J$1054,2015) -> 64017593 | C7: =SUMIFS('Raw Data'!$D$2:$D$1054,'Raw Data'!$J$2:$J$1054,2015) -> 1715089 | D7: =SUMIFS('Raw Data'!$G$2:$G$1054,'Raw Data'!$J$2:$J$1054,2015) -> -3899610.4 | E7: =D7/B7 -> -0.060914668 | F7: =AVERAGEIFS('Raw Data'!$E$2:$E$1054,'Raw Data'!$J$2:$J$1054,2015) -> 38.327482
A8: 2016 | B8: =SUMIFS('Raw Data'!$B$2:$B$1054,'Raw Data'!$J$2:$J$1054,2016) -> 46952976 | C8: =SUMIFS('Raw Data'!$D$2:$D$1054,'Raw Data'!$J$2:$J$1054,2016) -> 1294458 | D8: =SUMIFS('Raw Data'!$G$2:$G$1054,'Raw Data'!$J$2:$J$1054,2016) -> -938014.46 | E8: =D8/B8 -> -0.019977743 | F8: =AVERAGEIFS('Raw Data'!$E$2:$E$1054,'Raw Data'!$J$2:$J$1054,2016) -> 38.515993

Sheet Pivot - Day of Week
A1: Day-of-Week Pivot
A2: Built with AVERAGEIFS against Raw Data day_of_week column
A4: Day of Week | B4: Avg Daily Sales (R) | C4: Avg Daily Quantity | D4: Avg Price per Unit (R) | E4: Avg Gross Profit %
A5: Monday | B5: =AVERAGEIFS('Raw Data'!$B$2:$B$1054,'Raw Data'!$M$2:$M$1054,"Monday") -> 156313.03 | C5: =AVERAGEIFS('Raw Data'!$D$2:$D$1054,'Raw Data'!$M$2:$M$1054,"Monday") -> 4400.0464 | D5: =AVERAGEIFS('Raw Data'!$E$2:$E$1054,'Raw Data'!$M$2:$M$1054,"Monday") -> 37.242813 | E5: =AVERAGEIFS('Raw Data'!$H$2:$H$1054,'Raw Data'!$M$2:$M$1054,"Monday") -> -0.0042137865
A6: Tuesday | B6: =AVERAGEIFS('Raw Data'!$B$2:$B$1054,'Raw Data'!$M$2:$M$1054,"Tuesday") -> 137314.86 | C6: =AVERAGEIFS('Raw Data'!$D$2:$D$1054,'Raw Data'!$M$2:$M$1054,"Tuesday") -> 3851.702 | D6: =AVERAGEIFS('Raw Data'!$E$2:$E$1054,'Raw Data'!$M$2:$M$1054,"Tuesday") -> 37.232696 | E6: =AVERAGEIFS('Raw Data'!$H$2:$H$1054,'Raw Data'!$M$2:$M$1054,"Tuesday") -> -0.0041855288
A7: Wednesday | B7: =AVERAGEIFS('Raw Data'!$B$2:$B$1054,'Raw Data'!$M$2:$M$1054,"Wednesday") -> 145890.66 | C7: =AVERAGEIFS('Raw Data'!$D$2:$D$1054,'Raw Data'!$M$2:$M$1054,"Wednesday") -> 4105.9934 | D7: =AVERAGEIFS('Raw Data'!$E$2:$E$1054,'Raw Data'!$M$2:$M$1054,"Wednesday") -> 37.015791 | E7: =AVERAGEIFS('Raw Data'!$H$2:$H$1054,'Raw Data'!$M$2:$M$1054,"Wednesday") -> -0.0096822122
A8: Thursday | B8: =AVERAGEIFS('Raw Data'!$B$2:$B$1054,'Raw Data'!$M$2:$M$1054,"Thursday") -> 141084.76 | C8: =AVERAGEIFS('Raw Data'!$D$2:$D$1054,'Raw Data'!$M$2:$M$1054,"Thursday") -> 3969.22 | D8: =AVERAGEIFS('Raw Data'!$E$2:$E$1054,'Raw Data'!$M$2:$M$1054,"Thursday") -> 37.161422 | E8: =AVERAGEIFS('Raw Data'!$H$2:$H$1054,'Raw Data'!$M$2:$M$1054,"Thursday") -> -0.0055248025
A9: Friday | B9: =AVERAGEIFS('Raw Data'!$B$2:$B$1054,'Raw Data'!$M$2:$M$1054,"Friday") -> 245313.97 | C9: =AVERAGEIFS('Raw Data'!$D$2:$D$1054,'Raw Data'!$M$2:$M$1054,"Friday") -> 6955.3933 | D9: =AVERAGEIFS('Raw Data'!$E$2:$E$1054,'Raw Data'!$M$2:$M$1054,"Friday") -> 36.982263 | E9: =AVERAGEIFS('Raw Data'!$H$2:$H$1054,'Raw Data'!$M$2:$M$1054,"Friday") -> -0.011043695
A10: Saturday | B10: =AVERAGEIFS('Raw Data'!$B$2:$B$1054,'Raw Data'!$M$2:$M$1054,"Saturday") -> 279047.26 | C10: =AVERAGEIFS('Raw Data'!$D$2:$D$1054,'Raw Data'!$M$2:$M$1054,"Saturday") -> 7937.3067 | D10: =AVERAGEIFS('Raw Data'!$E$2:$E$1054,'Raw Data'!$M$2:$M$1054,"Saturday") -> 36.857654 | E10: =AVERAGEIFS('Raw Data'!$H$2:$H$1054,'Raw Data'!$M$2:$M$1054,"Saturday") -> -0.015141209
A11: Sunday | B11: =AVERAGEIFS('Raw Data'!$B$2:$B$1054,'Raw Data'!$M$2:$M$1054,"Sunday") -> 138170.86 | C11: =AVERAGEIFS('Raw Data'!$D$2:$D$1054,'Raw Data'!$M$2:$M$1054,"Sunday") -> 3897.1 | D11: =AVERAGEIFS('Raw Data'!$E$2:$E$1054,'Raw Data'!$M$2:$M$1054,"Sunday") -> 37.015503 | E11: =AVERAGEIFS('Raw Data'!$H$2:$H$1054,'Raw Data'!$M$2:$M$1054,"Sunday") -> -0.011511583

Sheet Pivot - Promo vs Non-Promo
A1: Promotional vs Non-Promotional Days
A2: promo_candidate flag: days with a notable price drop + quantity spike vs the trailing rolling average
A4: Segment | B4: # Days | C4: Avg Price per Unit (R) | D4: Avg Daily Quantity | E4: Avg Gross Profit %
A5: Non-Promotional | B5: =COUNTIFS('Raw Data'!$S$2:$S$1054,FALSE()) -> 925 | C5: =AVERAGEIFS('Raw Data'!$E$2:$E$1054,'Raw Data'!$S$2:$S$1054,FALSE()) -> 37.344364 | D5: =AVERAGEIFS('Raw Data'!$D$2:$D$1054,'Raw Data'!$S$2:$S$1054,FALSE()) -> 4634.9665 | E5: =AVERAGEIFS('Raw Data'!$H$2:$H$1054,'Raw Data'!$S$2:$S$1054,FALSE()) -> 0.00044409709
A6: Promotional | B6: =COUNTIFS('Raw Data'!$S$2:$S$1054,TRUE()) -> 128 | C6: =AVERAGEIFS('Raw Data'!$E$2:$E$1054,'Raw Data'!$S$2:$S$1054,TRUE()) -> 35.11075 | D6: =AVERAGEIFS('Raw Data'!$D$2:$D$1054,'Raw Data'!$S$2:$S$1054,TRUE()) -> 7754.125 | E6: =AVERAGEIFS('Raw Data'!$H$2:$H$1054,'Raw Data'!$S$2:$S$1054,TRUE()) -> -0.075189797

Sheet Promo Elasticity
A1: Metric 5 — Price Elasticity of Demand During Promotions
A2: Three promotional periods (longest contiguous "promo_candidate" runs) analysed against a 30-day pre-promotion, non-promotional baseline. PED = %Δ Quantity / %Δ Price.
A4: Period | B4: Promo Start | C4: Promo End | D4: Baseline Window (30 days pre-promo, excl. promo days) | E4: Baseline Avg Price (R) | F4: Promo Avg Price (R) | G4: % Δ Price | H4: Baseline Avg Qty | I4: Promo Avg Qty | J4: % Δ Qty | K4: Price Elasticity of Demand | L4: Baseline GP % | M4: Promo GP %
A5: Period 1 | B5: 42514 | C5: 42524 | D5: =TEXT(O5,"yyyy-mm-dd")&" to day before promo start" -> 2016-04-24 to day before promo start | E5: =AVERAGEIFS('Raw Data'!$E$2:$E$1054,'Raw Data'!$A$2:$A$1054,">="&$O5,'Raw Data'!$A$2:$A$1054,"<"&$B5,'Raw Data'!$S$2:$S$1054,FALSE()) -> 38.111765 | F5: =AVERAGEIFS('Raw Data'!$E$2:$E$1054,'Raw Data'!$A$2:$A$1054,">="&$B5,'Raw Data'!$A$2:$A$1054,"<="&$C5) -> 34.352331 | G5: =(F5-E5)/E5 -> -0.098642346 | H5: =AVERAGEIFS('Raw Data'!$D$2:$D$1054,'Raw Data'!$A$2:$A$1054,">="&$O5,'Raw Data'!$A$2:$A$1054,"<"&$B5,'Raw Data'!$S$2:$S$1054,FALSE()) -> 5203.8667 | I5: =AVERAGEIFS('Raw Data'!$D$2:$D$1054,'Raw Data'!$A$2:$A$1054,">="&$B5,'Raw Data'!$A$2:$A$1054,"<="&$C5) -> 7935.8182 | J5: =(I5-H5)/H5 -> 0.52498492 | K5: =J5/G5 -> -5.3221049 | L5: =AVERAGEIFS('Raw Data'!$H$2:$H$1054,'Raw Data'!$A$2:$A$1054,">="&$O5,'Raw Data'!$A$2:$A$1054,"<"&$B5,'Raw Data'!$S$2:$S$1054,FALSE()) -> 0.028935827 | M5: =AVERAGEIFS('Raw Data'!$H$2:$H$1054,'Raw Data'!$A$2:$A$1054,">="&$B5,'Raw Data'!$A$2:$A$1054,"<="&$C5) -> -0.059367305 | O5: 42484
A6: Period 2 | B6: 42270 | C6: 42279 | D6: =TEXT(O6,"yyyy-mm-dd")&" to day before promo start" -> 2015-08-24 to day before promo start | E6: =AVERAGEIFS('Raw Data'!$E$2:$E$1054,'Raw Data'!$A$2:$A$1054,">="&$O6,'Raw Data'!$A$2:$A$1054,"<"&$B6,'Raw Data'!$S$2:$S$1054,FALSE()) -> 37.948221 | F6: =AVERAGEIFS('Raw Data'!$E$2:$E$1054,'Raw Data'!$A$2:$A$1054,">="&$B6,'Raw Data'!$A$2:$A$1054,"<="&$C6) -> 33.404647 | G6: =(F6-E6)/E6 -> -0.11973089 | H6: =AVERAGEIFS('Raw Data'!$D$2:$D$1054,'Raw Data'!$A$2:$A$1054,">="&$O6,'Raw Data'!$A$2:$A$1054,"<"&$B6,'Raw Data'!$S$2:$S$1054,FALSE()) -> 2887.381 | I6: =AVERAGEIFS('Raw Data'!$D$2:$D$1054,'Raw Data'!$A$2:$A$1054,">="&$B6,'Raw Data'!$A$2:$A$1054,"<="&$C6) -> 7819.4 | J6: =(I6-H6)/H6 -> 1.708129 | K6: =J6/G6 -> -14.266402 | L6: =AVERAGEIFS('Raw Data'!$H$2:$H$1054,'Raw Data'!$A$2:$A$1054,">="&$O6,'Raw Data'!$A$2:$A$1054,"<"&$B6,'Raw Data'!$S$2:$S$1054,FALSE()) -> 0.020200961 | M6: =AVERAGEIFS('Raw Data'!$H$2:$H$1054,'Raw Data'!$A$2:$A$1054,">="&$B6,'Raw Data'!$A$2:$A$1054,"<="&$C6) -> -0.13083613 | O6: 42240
A7: Period 3 | B7: 42391 | C7: 42399 | D7: =TEXT(O7,"yyyy-mm-dd")&" to day before promo start" -> 2015-12-23 to day before promo start | E7: =AVERAGEIFS('Raw Data'!$E$2:$E$1054,'Raw Data'!$A$2:$A$1054,">="&$O7,'Raw Data'!$A$2:$A$1054,"<"&$B7,'Raw Data'!$S$2:$S$1054,FALSE()) -> 40.156123 | F7: =AVERAGEIFS('Raw Data'!$E$2:$E$1054,'Raw Data'!$A$2:$A$1054,">="&$B7,'Raw Data'!$A$2:$A$1054,"<="&$C7) -> 34.056916 | G7: =(F7-E7)/E7 -> -0.15188735 | H7: =AVERAGEIFS('Raw Data'!$D$2:$D$1054,'Raw Data'!$A$2:$A$1054,">="&$O7,'Raw Data'!$A$2:$A$1054,"<"&$B7,'Raw Data'!$S$2:$S$1054,FALSE()) -> 3268.96 | I7: =AVERAGEIFS('Raw Data'!$D$2:$D$1054,'Raw Data'!$A$2:$A$1054,">="&$B7,'Raw Data'!$A$2:$A$1054,"<="&$C7) -> 8096.6667 | J7: =(I7-H7)/H7 -> 1.4768326 | K7: =J7/G7 -> -9.7232099 | L7: =AVERAGEIFS('Raw Data'!$H$2:$H$1054,'Raw Data'!$A$2:$A$1054,">="&$O7,'Raw Data'!$A$2:$A$1054,"<"&$B7,'Raw Data'!$S$2:$S$1054,FALSE()) -> 0.04614042 | M7: =AVERAGEIFS('Raw Data'!$H$2:$H$1054,'Raw Data'!$A$2:$A$1054,">="&$B7,'Raw Data'!$A$2:$A$1054,"<="&$C7) -> -0.091084654 | O7: 42361
A10: Interpretation
A11: All three periods show highly elastic demand (|PED| well above 1): a ~10–15% price cut during promotion drives a 50–170% jump in average daily quantity sold. However, promotional gross profit % turns negative in every period (baseline was positive, +2% to +5%), while promo-period margin falls to roughly -6% to -13%. In other words, the discount depth is currently cutting deeper than the volume uplift can compensate for — the product sells far better by units at a promotional price, but the store loses money doing it under this pricing structure. A shallower discount (e.g. 5-8% instead of 10-15%) would likely still trigger a large volume response given how elastic demand is, while keeping gross margin closer to breakeven or positive.
